{"page": {"num": 1, "size": 20, "count": 810, "acount": 810}, "config": {"showtopic": 1, "show_up_flag": true, "read_only": false}, "replies": [{"rpid": 230665005552, "oid": 1156233854, "type": 1, "mid": 279241930, "root": 0, "parent": 0, "dialog": 0, "count": 0, "rcount": 0, "state": 0, "fansgrade": 0, "attr": 0, "ctime": 1720596561, "mid_str": "279241930", "oid_str": "1156233854", "rpid_str": "230665005552", "root_str": "0", "parent_str": "0", "dialog_str": "0", "like": 0, "action": 0, "member": {"mid": "279241930", "uname": "\u7368\u306e\u767d", "sex": "\u4fdd\u5bc6", "sign": "", "avatar": "https://i1.hdslb.com/bfs/face/90a9d3e262ce45a02322830c466a4c7ebe5fd370.jpg", "rank": "10000", "face_nft_new": 0, "is_senior_member": 0, "senior": {}, "level_info": {"current_level": 6, "current_min": 0, "current_exp": 0, "next_exp": 0}, "pendant": {"pid": 0, "name": "", "image": "", "expire": 0, "image_enhance": "", "image_enhance_frame": "", "n_pid": 0}, "nameplate": {"nid": 0, "name": "", "image": "", "image_small": "", "level": "", "condition": ""}, "official_verify": {"type": -1, "desc": ""}, "vip": {"vipType": 1, "vipDueDate": 1626451200000, "dueRemark": "", "accessStatus": 0, "vipStatus": 0, "vipStatusWarn": "", "themeType": 0, "label": {"path": "", "text": "", "label_theme": "", "text_color": "", "bg_style": 0, "bg_color": "", "border_color": "", "use_img_label": true, "img_label_uri_hans": "", "img_label_uri_hant": "", "img_label_uri_hans_static": "https://i0.hdslb.com/bfs/vip/d7b702ef65a976b20ed854cbd04cb9e27341bb79.png", "img_label_uri_hant_static": "https://i0.hdslb.com/bfs/activity-plat/static/20220614/e369244d0b14644f5e1a06431e22a4d5/KJunwh19T5.png"}, "avatar_subscript": 0, "nickname_color": ""}, "fans_detail": null, "user_sailing": null, "is_contractor": false, "contract_desc": "", "nft_interaction": null, "avatar_item": {"container_size": {"width": 1.8, "height": 1.8}, "fallback_layers": {"layers": [{"visible": true, "general_spec": {"pos_spec": {"coordinate_pos": 2, "axis_x": 0.9, "axis_y": 0.9}, "size_spec": {"width": 1, "height": 1}, "render_spec": {"opacity": 1}}, "layer_config": {"tags": {"AVATAR_LAYER": {}, "GENERAL_CFG": {"config_type": 1, "general_config": {"web_css_style": {"borderRadius": "50%"}}}}, "is_critical": true}, "resource": {"res_type": 3, "res_image": {"image_src": {"src_type": 1, "placeholder": 6, "remote": {"url": "https://i1.hdslb.com/bfs/face/90a9d3e262ce45a02322830c466a4c7ebe5fd370.jpg", "bfs_style": "widget-layer-avatar"}}}}}], "is_critical_group": true}, "mid": "279241930"}}, "content": {"message": "\u4e3a\u4ec0\u4e48\u611f\u89c9\u8fd9\u89c6\u9891\u597d\u4e45\u524d\u5c31\u770b\u8fc7", "members": [], "jump_url": {}, "max_line": 6}, "replies": [], "assist": 0, "up_action": {"like": false, "reply": false}, "invisible": false, "reply_control": {"max_line": 6, "time_desc": "1\u5206\u949f\u524d\u53d1\u5e03"}, "folder": {"has_folded": false, "is_folded": false, "rule": ""}, "dynamic_id_str": "0", "note_cvid_str": "0", "track_info": ""}, {"rpid": 230663472752, "oid": 1156233854, "type": 1, "mid": 3546594284669041, "root": 0, "parent": 0, "dialog": 0, "count": 0, "rcount": 0, "state": 0, "fansgrade": 0, "attr": 0, "ctime": 1720595903, "mid_str": "3546594284669041", "oid_str": "1156233854", "rpid_str": "230663472752", "root_str": "0", "parent_str": "0", "dialog_str": "0", "like": 0, "action": 0, "member": {"mid": "3546594284669041", "uname": "\u4e07\u5e74\u4e0d\u53d8\u771f\u4e0d\u53d8", "sex": "\u4fdd\u5bc6", "sign": "", "avatar": "https://i0.hdslb.com/bfs/face/member/noface.jpg", "rank": "10000", "face_nft_new": 0, "is_senior_member": 0, "senior": {}, "level_info": {"current_level": 3, "current_min": 0, "current_exp": 0, "next_exp": 0}, "pendant": {"pid": 0, "name": "", "image": "", "expire": 0, "image_enhance": "", "image_enhance_frame": "", "n_pid": 0}, "nameplate": {"nid": 0, "name": "", "image": "", "image_small": "", "level": "", "condition": ""}, "official_verify": {"type": -1, "desc": ""}, "vip": {"vipType": 1, "vipDueDate": 1722441600000, "dueRemark": "", "accessStatus": 0, "vipStatus": 1, "vipStatusWarn": "", "themeType": 0, "label": {"path": "", "text": "\u5927\u4f1a\u5458", "label_theme": "vip", "text_color": "#FFFFFF", "bg_style": 1, "bg_color": "#FB7299", "border_color": "", "use_img_label": true, "img_label_uri_hans": "", "img_label_uri_hant": "", "img_label_uri_hans_static": "https://i0.hdslb.com/bfs/vip/3788b674c69072f1ee252b79a31ecc8c43af3039.png", "img_label_uri_hant_static": "https://i0.hdslb.com/bfs/activity-plat/static/20220614/e369244d0b14644f5e1a06431e22a4d5/jwXBWRVwa5.png"}, "avatar_subscript": 1, "nickname_color": "#FB7299"}, "fans_detail": null, "user_sailing": null, "is_contractor": false, "contract_desc": "", "nft_interaction": null, "avatar_item": {"container_size": {"width": 1.8, "height": 1.8}, "fallback_layers": {"layers": [{"visible": true, "general_spec": {"pos_spec": {"coordinate_pos": 2, "axis_x": 0.9, "axis_y": 0.9}, "size_spec": {"width": 1, "height": 1}, "render_spec": {"opacity": 1}}, "layer_config": {"tags": {"AVATAR_LAYER": {}, "GENERAL_CFG": {"config_type": 1, "general_config": {"web_css_style": {"borderRadius": "50%"}}}}, "is_critical": true}, "resource": {"res_type": 3, "res_image": {"image_src": {"src_type": 1, "placeholder": 6, "remote": {"url": "https://i0.hdslb.com/bfs/face/member/noface.jpg", "bfs_style": "widget-layer-avatar"}}}}}, {"visible": true, "general_spec": {"pos_spec": {"coordinate_pos": 1, "axis_x": 1.025, "axis_y": 1.025}, "size_spec": {"width": 0.41666666666666663, "height": 0.41666666666666663}, "render_spec": {"opacity": 1}}, "layer_config": {"tags": {"GENERAL_CFG": {"config_type": 1, "general_config": {"web_css_style": {"background-color": "rgb(255,255,255)", "border": "2px solid rgba(255,255,255,1)", "borderRadius": "50%", "boxSizing": "border-box"}}}, "ICON_LAYER": {}}}, "resource": {"res_type": 3, "res_image": {"image_src": {"src_type": 2, "local": 1}}}}], "is_critical_group": true}, "mid": "3546594284669041"}}, "content": {"message": "\u773c\u91cc\u6709\u5149", "members": [], "jump_url": {}, "max_line": 6}, "replies": [], "assist": 0, "up_action": {"like": false, "reply": false}, "invisible": false, "reply_control": {"max_line": 6, "time_desc": "12\u5206\u949f\u524d\u53d1\u5e03"}, "folder": {"has_folded": false, "is_folded": false, "rule": ""}, "dynamic_id_str": "0", "note_cvid_str": "0", "track_info": ""}, {"rpid": 230653912160, "oid": 1156233854, "type": 1, "mid": 587970173, "root": 0, "parent": 0, "dialog": 0, "count": 0, "rcount": 0, "state": 0, "fansgrade": 0, "attr": 0, "ctime": 1720591830, "mid_str": "587970173", "oid_str": "1156233854", "rpid_str": "230653912160", "root_str": "0", "parent_str": "0", "dialog_str": "0", "like": 0, "action": 0, "member": {"mid": "587970173", "uname": "\u963f\u62c9\u65af\u52a0\u5495\u5495", "sex": "\u4fdd\u5bc6", "sign": "", "avatar": "https://i2.hdslb.com/bfs/face/eaeddeea9261c29f7c9f7e6a6cb6e536596e3a45.jpg", "rank": "10000", "face_nft_new": 0, "is_senior_member": 0, "senior": {}, "level_info": {"current_level": 5, "current_min": 0, "current_exp": 0, "next_exp": 0}, "pendant": {"pid": 0, "name": "", "image": "", "expire": 0, "image_enhance": "", "image_enhance_frame": "", "n_pid": 0}, "nameplate": {"nid": 0, "name": "", "image": "", "image_small": "", "level": "", "condition": ""}, "official_verify": {"type": -1, "desc": ""}, "vip": {"vipType": 0, "vipDueDate": 0, "dueRemark": "", "accessStatus": 0, "vipStatus": 0, "vipStatusWarn": "", "themeType": 0, "label": {"path": "", "text": "", "label_theme": "", "text_color": "", "bg_style": 0, "bg_color": "", "border_color": "", "use_img_label": true, "img_label_uri_hans": "", "img_label_uri_hant": "", "img_label_uri_hans_static": "https://i0.hdslb.com/bfs/vip/d7b702ef65a976b20ed854cbd04cb9e27341bb79.png", "img_label_uri_hant_static": "https://i0.hdslb.com/bfs/activity-plat/static/20220614/e369244d0b14644f5e1a06431e22a4d5/KJunwh19T5.png"}, "avatar_subscript": 0, "nickname_color": ""}, "fans_detail": null, "user_sailing": null, "is_contractor": false, "contract_desc": "", "nft_interaction": null, "avatar_item": {"container_size": {"width": 1.8, "height": 1.8}, "fallback_layers": {"layers": [{"visible": true, "general_spec": {"pos_spec": {"coordinate_pos": 2, "axis_x": 0.9, "axis_y": 0.9}, "size_spec": {"width": 1, "height": 1}, "render_spec": {"opacity": 1}}, "layer_config": {"tags": {"AVATAR_LAYER": {}, "GENERAL_CFG": {"config_type": 1, "general_config": {"web_css_style": {"borderRadius": "50%"}}}}, "is_critical": true}, "resource": {"res_type": 3, "res_image": {"image_src": {"src_type": 1, "placeholder": 6, "remote": {"url": "https://i2.hdslb.com/bfs/face/eaeddeea9261c29f7c9f7e6a6cb6e536596e3a45.jpg", "bfs_style": "widget-layer-avatar"}}}}}], "is_critical_group": true}, "mid": "587970173"}}, "content": {"message": "\u611f\u52a8", "members": [], "jump_url": {}, "max_line": 6}, "replies": [], "assist": 0, "up_action": {"like": false, "reply": false}, "invisible": false, "reply_control": {"max_line": 6, "time_desc": "1\u5c0f\u65f6\u524d\u53d1\u5e03"}, "folder": {"has_folded": false, "is_folded": false, "rule": ""}, "dynamic_id_str": "0", "note_cvid_str": "0", "track_info": ""}, {"rpid": 230652242816, "oid": 1156233854, "type": 1, "mid": 1785417732, "root": 0, "parent": 0, "dialog": 0, "count": 0, "rcount": 0, "state": 0, "fansgrade": 0, "attr": 0, "ctime": 1720591073, "mid_str": "1785417732", "oid_str": "1156233854", "rpid_str": "230652242816", "root_str": "0", "parent_str": "0", "dialog_str": "0", "like": 0, "action": 0, "member": {"mid": "1785417732", "uname": "\u4e1c\u8fb9\u90a3\u4e2a\u5c0f\u9053\u58eb", "sex": "\u4fdd\u5bc6", "sign": "", "avatar": "https://i0.hdslb.com/bfs/face/9f6502fb3ca343f47039d0e4b3ef2205ae5afd32.jpg", "rank": "10000", "face_nft_new": 0, "is_senior_member": 0, "senior": {}, "level_info": {"current_level": 4, "current_min": 0, "current_exp": 0, "next_exp": 0}, "pendant": {"pid": 0, "name": "", "image": "", "expire": 0, "image_enhance": "", "image_enhance_frame": "", "n_pid": 0}, "nameplate": {"nid": 0, "name": "", "image": "", "image_small": "", "level": "", "condition": ""}, "official_verify": {"type": -1, "desc": ""}, "vip": {"vipType": 1, "vipDueDate": 1633968000000, "dueRemark": "", "accessStatus": 0, "vipStatus": 0, "vipStatusWarn": "", "themeType": 0, "label": {"path": "", "text": "", "label_theme": "", "text_color": "", "bg_style": 0, "bg_color": "", "border_color": "", "use_img_label": true, "img_label_uri_hans": "", "img_label_uri_hant": "", "img_label_uri_hans_static": "https://i0.hdslb.com/bfs/vip/d7b702ef65a976b20ed854cbd04cb9e27341bb79.png", "img_label_uri_hant_static": "https://i0.hdslb.com/bfs/activity-plat/static/20220614/e369244d0b14644f5e1a06431e22a4d5/KJunwh19T5.png"}, "avatar_subscript": 0, "nickname_color": ""}, "fans_detail": null, "user_sailing": null, "is_contractor": false, "contract_desc": "", "nft_interaction": null, "avatar_item": {"container_size": {"width": 1.8, "height": 1.8}, "fallback_layers": {"layers": [{"visible": true, "general_spec": {"pos_spec": {"coordinate_pos": 2, "axis_x": 0.9, "axis_y": 0.9}, "size_spec": {"width": 1, "height": 1}, "render_spec": {"opacity": 1}}, "layer_config": {"tags": {"AVATAR_LAYER": {}, "GENERAL_CFG": {"config_type": 1, "general_config": {"web_css_style": {"borderRadius": "50%"}}}}, "is_critical": true}, "resource": {"res_type": 3, "res_image": {"image_src": {"src_type": 1, "placeholder": 6, "remote": {"url": "https://i0.hdslb.com/bfs/face/9f6502fb3ca343f47039d0e4b3ef2205ae5afd32.jpg", "bfs_style": "widget-layer-avatar"}}}}}], "is_critical_group": true}, "mid": "1785417732"}}, "content": {"message": "\u8fd9\u5c31\u662f\u771f\u6b63\u4e2d\u56fd\u4eba\uff0c\u6da6\u4eba\u7406\u89e3\u4e0d\u4e86", "members": [], "jump_url": {}, "max_line": 6}, "replies": [], "assist": 0, "up_action": {"like": false, "reply": false}, "invisible": false, "reply_control": {"max_line": 6, "time_desc": "1\u5c0f\u65f6\u524d\u53d1\u5e03"}, "folder": {"has_folded": false, "is_folded": false, "rule": ""}, "dynamic_id_str": "0", "note_cvid_str": "0", "track_info": ""}, {"rpid": 230644105728, "oid": 1156233854, "type": 1, "mid": 10720096, "root": 0, "parent": 0, "dialog": 0, "count": 0, "rcount": 0, "state": 0, "fansgrade": 0, "attr": 0, "ctime": 1720588032, "mid_str": "10720096", "oid_str": "1156233854", "rpid_str": "230644105728", "root_str": "0", "parent_str": "0", "dialog_str": "0", "like": 0, "action": 0, "member": {"mid": "10720096", "uname": "\u6d77\u4e36\u5ddd", "sex": "\u7537", "sign": "\u6625\u751f\uff0c\u590f\u957f\uff0c\u79cb\u6536\uff0c\u51ac\u85cf\u3002", "avatar": "https://i1.hdslb.com/bfs/face/b64eb1145bcd7a3b5d497d981bc9f7a76767c588.jpg", "rank": "10000", "face_nft_new": 0, "is_senior_member": 0, "senior": {}, "level_info": {"current_level": 6, "current_min": 0, "current_exp": 0, "next_exp": 0}, "pendant": {"pid": 0, "name": "", "image": "", "expire": 0, "image_enhance": "", "image_enhance_frame": "", "n_pid": 0}, "nameplate": {"nid": 0, "name": "", "image": "", "image_small": "", "level": "", "condition": ""}, "official_verify": {"type": -1, "desc": ""}, "vip": {"vipType": 1, "vipDueDate": 1657728000000, "dueRemark": "", "accessStatus": 0, "vipStatus": 0, "vipStatusWarn": "", "themeType": 0, "label": {"path": "", "text": "", "label_theme": "", "text_color": "", "bg_style": 0, "bg_color": "", "border_color": "", "use_img_label": true, "img_label_uri_hans": "", "img_label_uri_hant": "", "img_label_uri_hans_static": "https://i0.hdslb.com/bfs/vip/d7b702ef65a976b20ed854cbd04cb9e27341bb79.png", "img_label_uri_hant_static": "https://i0.hdslb.com/bfs/activity-plat/static/20220614/e369244d0b14644f5e1a06431e22a4d5/KJunwh19T5.png"}, "avatar_subscript": 0, "nickname_color": ""}, "fans_detail": null, "user_sailing": null, "is_contractor": false, "contract_desc": "", "nft_interaction": null, "avatar_item": {"container_size": {"width": 1.8, "height": 1.8}, "fallback_layers": {"layers": [{"visible": true, "general_spec": {"pos_spec": {"coordinate_pos": 2, "axis_x": 0.9, "axis_y": 0.9}, "size_spec": {"width": 1, "height": 1}, "render_spec": {"opacity": 1}}, "layer_config": {"tags": {"AVATAR_LAYER": {}, "GENERAL_CFG": {"config_type": 1, "general_config": {"web_css_style": {"borderRadius": "50%"}}}}, "is_critical": true}, "resource": {"res_type": 3, "res_image": {"image_src": {"src_type": 1, "placeholder": 6, "remote": {"url": "https://i1.hdslb.com/bfs/face/b64eb1145bcd7a3b5d497d981bc9f7a76767c588.jpg", "bfs_style": "widget-layer-avatar"}}}}}], "is_critical_group": true}, "mid": "10720096"}}, "content": {"message": "\u6709\u4e9b\u4eba\uff0c\u4e00\u751f\u53ea\u5728\u4e00\u4e2a\u5730\u65b9\u3002", "members": [], "jump_url": {}, "max_line": 6}, "replies": [], "assist": 0, "up_action": {"like": false, "reply": false}, "invisible": false, "reply_control": {"max_line": 6, "time_desc": "2\u5c0f\u65f6\u524d\u53d1\u5e03"}, "folder": {"has_folded": false, "is_folded": false, "rule": ""}, "dynamic_id_str": "0", "note_cvid_str": "0", "track_info": ""}, {"rpid": 230638849936, "oid": 1156233854, "type": 1, "mid": 1866334758, "root": 0, "parent": 0, "dialog": 0, "count": 0, "rcount": 0, "state": 0, "fansgrade": 0, "attr": 0, "ctime": 1720586384, "mid_str": "1866334758", "oid_str": "1156233854", "rpid_str": "230638849936", "root_str": "0", "parent_str": "0", "dialog_str": "0", "like": 0, "action": 0, "member": {"mid": "1866334758", "uname": "14789632555", "sex": "\u4fdd\u5bc6", "sign": "", "avatar": "https://i0.hdslb.com/bfs/face/member/noface.jpg", "rank": "10000", "face_nft_new": 0, "is_senior_member": 0, "senior": {}, "level_info": {"current_level": 3, "current_min": 0, "current_exp": 0, "next_exp": 0}, "pendant": {"pid": 0, "name": "", "image": "", "expire": 0, "image_enhance": "", "image_enhance_frame": "", "n_pid": 0}, "nameplate": {"nid": 0, "name": "", "image": "", "image_small": "", "level": "", "condition": ""}, "official_verify": {"type": -1, "desc": ""}, "vip": {"vipType": 0, "vipDueDate": 0, "dueRemark": "", "accessStatus": 0, "vipStatus": 0, "vipStatusWarn": "", "themeType": 0, "label": {"path": "", "text": "", "label_theme": "", "text_color": "", "bg_style": 0, "bg_color": "", "border_color": "", "use_img_label": true, "img_label_uri_hans": "", "img_label_uri_hant": "", "img_label_uri_hans_static": "https://i0.hdslb.com/bfs/vip/d7b702ef65a976b20ed854cbd04cb9e27341bb79.png", "img_label_uri_hant_static": "https://i0.hdslb.com/bfs/activity-plat/static/20220614/e369244d0b14644f5e1a06431e22a4d5/KJunwh19T5.png"}, "avatar_subscript": 0, "nickname_color": ""}, "fans_detail": null, "user_sailing": null, "is_contractor": false, "contract_desc": "", "nft_interaction": null, "avatar_item": {"container_size": {"width": 1.8, "height": 1.8}, "fallback_layers": {"layers": [{"visible": true, "general_spec": {"pos_spec": {"coordinate_pos": 2, "axis_x": 0.9, "axis_y": 0.9}, "size_spec": {"width": 1, "height": 1}, "render_spec": {"opacity": 1}}, "layer_config": {"tags": {"AVATAR_LAYER": {}, "GENERAL_CFG": {"config_type": 1, "general_config": {"web_css_style": {"borderRadius": "50%"}}}}, "is_critical": true}, "resource": {"res_type": 3, "res_image": {"image_src": {"src_type": 1, "placeholder": 6, "remote": {"url": "https://i0.hdslb.com/bfs/face/member/noface.jpg", "bfs_style": "widget-layer-avatar"}}}}}], "is_critical_group": true}, "mid": "1866334758"}}, "content": {"message": "\u6d3b\u7684\u660e\u767d\uff0c\u655e\u4eae\uff0c\u4f69\u670d[\u5472\u7259]", "members": [], "emote": {"[\u5472\u7259]": {"id": 1902, "package_id": 1, "state": 0, "type": 1, "attr": 0, "text": "[\u5472\u7259]", "url": "https://i0.hdslb.com/bfs/emote/b5a5898491944a4268360f2e7a84623149672eb6.png", "meta": {"size": 1, "suggest": [""]}, "mtime": 1668688325, "jump_title": "\u5472\u7259"}}, "jump_url": {}, "max_line": 6}, "replies": [], "assist": 0, "up_action": {"like": false, "reply": false}, "invisible": false, "reply_control": {"max_line": 6, "time_desc": "2\u5c0f\u65f6\u524d\u53d1\u5e03"}, "folder": {"has_folded": false, "is_folded": false, "rule": ""}, "dynamic_id_str": "0", "note_cvid_str": "0", "track_info": ""}, {"rpid": 230613174656, "oid": 1156233854, "type": 1, "mid": 38019808, "root": 0, "parent": 0, "dialog": 0, "count": 1, "rcount": 1, "state": 0, "fansgrade": 0, "attr": 0, "ctime": 1720576622, "mid_str": "38019808", "oid_str": "1156233854", "rpid_str": "230613174656", "root_str": "0", "parent_str": "0", "dialog_str": "0", "like": 0, "action": 0, "member": {"mid": "38019808", "uname": "\u5854\u8fbe\u6797\u54d4\u683c\u7b2c\u4e00\u4eba", "sex": "\u7537", "sign": "\u5fc3\u4f3c\u53cc\u4e1d\u7f51 \u4e2d\u6709\u5343\u5343\u7ed3", "avatar": "https://i1.hdslb.com/bfs/face/36295dbcc5cf00929ac181a59cad78731c184c4d.jpg", "rank": "10000", "face_nft_new": 0, "is_senior_member": 0, "senior": {}, "level_info": {"current_level": 6, "current_min": 0, "current_exp": 0, "next_exp": 0}, "pendant": {"pid": 0, "name": "", "image": "", "expire": 0, "image_enhance": "", "image_enhance_frame": "", "n_pid": 0}, "nameplate": {"nid": 74, "name": "\u5927\u4f1a\u54582018\u5e74\u5ea6\u52cb\u7ae0", "image": "https://i0.hdslb.com/bfs/face/421179426c929dfeaed4117461c83f5d07ffb148.png", "image_small": "https://i2.hdslb.com/bfs/face/682001c2e1c2ae887bdf2a0e18eef61180c48f84.png", "level": "\u7a00\u6709\u52cb\u7ae0", "condition": "2018.6.26-7.8\u67d0\u4e00\u5929\u662f\u5e74\u5ea6\u5927\u4f1a\u5458"}, "official_verify": {"type": -1, "desc": ""}, "vip": {"vipType": 2, "vipDueDate": 1756137600000, "dueRemark": "", "accessStatus": 0, "vipStatus": 1, "vipStatusWarn": "", "themeType": 0, "label": {"path": "", "text": "\u5e74\u5ea6\u5927\u4f1a\u5458", "label_theme": "annual_vip", "text_color": "#FFFFFF", "bg_style": 1, "bg_color": "#FB7299", "border_color": "", "use_img_label": true, "img_label_uri_hans": "", "img_label_uri_hant": "", "img_label_uri_hans_static": "https://i0.hdslb.com/bfs/vip/8d4f8bfc713826a5412a0a27eaaac4d6b9ede1d9.png", "img_label_uri_hant_static": "https://i0.hdslb.com/bfs/activity-plat/static/20220614/e369244d0b14644f5e1a06431e22a4d5/VEW8fCC0hg.png"}, "avatar_subscript": 1, "nickname_color": "#FB7299"}, "fans_detail": null, "user_sailing": null, "is_contractor": false, "contract_desc": "", "nft_interaction": null, "avatar_item": {"container_size": {"width": 1.8, "height": 1.8}, "fallback_layers": {"layers": [{"visible": true, "general_spec": {"pos_spec": {"coordinate_pos": 2, "axis_x": 0.9, "axis_y": 0.9}, "size_spec": {"width": 1, "height": 1}, "render_spec": {"opacity": 1}}, "layer_config": {"tags": {"AVATAR_LAYER": {}, "GENERAL_CFG": {"config_type": 1, "general_config": {"web_css_style": {"borderRadius": "50%"}}}}, "is_critical": true}, "resource": {"res_type": 3, "res_image": {"image_src": {"src_type": 1, "placeholder": 6, "remote": {"url": "https://i1.hdslb.com/bfs/face/36295dbcc5cf00929ac181a59cad78731c184c4d.jpg", "bfs_style": "widget-layer-avatar"}}}}}, {"visible": true, "general_spec": {"pos_spec": {"coordinate_pos": 1, "axis_x": 1.025, "axis_y": 1.025}, "size_spec": {"width": 0.41666666666666663, "height": 0.41666666666666663}, "render_spec": {"opacity": 1}}, "layer_config": {"tags": {"GENERAL_CFG": {"config_type": 1, "general_config": {"web_css_style": {"background-color": "rgb(255,255,255)", "border": "2px solid rgba(255,255,255,1)", "borderRadius": "50%", "boxSizing": "border-box"}}}, "ICON_LAYER": {}}}, "resource": {"res_type": 3, "res_image": {"image_src": {"src_type": 2, "local": 1}}}}], "is_critical_group": true}, "mid": "38019808"}}, "content": {"message": "\u4e3a\u4ec0\u4e48\u8bc4\u8bba\u533a\u90fd\u5728\u8bf4\u8fd9\u4e2a\u70e7\u6c34\u597d\u559d\u554a\uff1f\u771f\u559d\u8fc7\u8fd8\u662f\u5047\u559d\u8fc7\u554a\uff1f", "members": [], "jump_url": {"\u70e7\u6c34": {"title": "\u70e7\u6c34", "state": 0, "prefix_icon": "https://i0.hdslb.com/bfs/reply/9f3ad0659e84c96a711b88dd33f4bc2e945045e0.png", "app_url_schema": "bilibili://search?from=appcommentline_search&search_from_source=appcommentline_search&direct_return=true&keyword=%E7%83%A7%E6%B0%B4&seid=7004122714792251788", "app_name": "", "app_package_name": "", "click_report": "", "is_half_screen": false, "exposure_report": "", "extra": {"goods_show_type": 0, "is_word_search": true, "goods_cm_control": 0, "goods_click_report": "", "goods_exposure_report": ""}, "underline": false, "match_once": true, "pc_url": "//search.bilibili.com/all?from_source=webcommentline_search&keyword=%E7%83%A7%E6%B0%B4&seid=7004122714792251788", "icon_position": 1}}, "max_line": 6}, "replies": [{"rpid": 230651197776, "oid": 1156233854, "type": 1, "mid": 649919349, "root": 230613174656, "parent": 230613174656, "dialog": 230651197776, "count": 0, "rcount": 0, "state": 0, "fansgrade": 0, "attr": 0, "ctime": 1720590716, "mid_str": "649919349", "oid_str": "1156233854", "rpid_str": "230651197776", "root_str": "230613174656", "parent_str": "230613174656", "dialog_str": "230651197776", "like": 0, "action": 0, "member": {"mid": "649919349", "uname": "\u770b\u5230\u6211\u63d0\u9192\u6211\u5b66\u4e60", "sex": "\u4fdd\u5bc6", "sign": "", "avatar": "http://i0.hdslb.com/bfs/face/3468c648fe3109f3d647b1307ac8b6c519381a98.jpg", "rank": "10000", "face_nft_new": 0, "is_senior_member": 0, "senior": {}, "level_info": {"current_level": 5, "current_min": 0, "current_exp": 0, "next_exp": 0}, "pendant": {"pid": 0, "name": "", "image": "", "expire": 0, "image_enhance": "", "image_enhance_frame": "", "n_pid": 0}, "nameplate": {"nid": 0, "name": "", "image": "", "image_small": "", "level": "", "condition": ""}, "official_verify": {"type": -1, "desc": ""}, "vip": {"vipType": 1, "vipDueDate": 1640016000000, "dueRemark": "", "accessStatus": 0, "vipStatus": 0, "vipStatusWarn": "", "themeType": 0, "label": {"path": "", "text": "", "label_theme": "", "text_color": "", "bg_style": 0, "bg_color": "", "border_color": "", "use_img_label": true, "img_label_uri_hans": "", "img_label_uri_hant": "", "img_label_uri_hans_static": "https://i0.hdslb.com/bfs/vip/d7b702ef65a976b20ed854cbd04cb9e27341bb79.png", "img_label_uri_hant_static": "https://i0.hdslb.com/bfs/activity-plat/static/20220614/e369244d0b14644f5e1a06431e22a4d5/KJunwh19T5.png"}, "avatar_subscript": 0, "nickname_color": ""}, "fans_detail": null, "user_sailing": null, "is_contractor": false, "contract_desc": "", "nft_interaction": null, "avatar_item": {"container_size": {"width": 1.8, "height": 1.8}, "fallback_layers": {"layers": [{"visible": true, "general_spec": {"pos_spec": {"coordinate_pos": 2, "axis_x": 0.9, "axis_y": 0.9}, "size_spec": {"width": 1, "height": 1}, "render_spec": {"opacity": 1}}, "layer_config": {"tags": {"AVATAR_LAYER": {}, "GENERAL_CFG": {"config_type": 1, "general_config": {"web_css_style": {"borderRadius": "50%"}}}}, "is_critical": true}, "resource": {"res_type": 3, "res_image": {"image_src": {"src_type": 1, "placeholder": 6, "remote": {"url": "http://i0.hdslb.com/bfs/face/3468c648fe3109f3d647b1307ac8b6c519381a98.jpg", "bfs_style": "widget-layer-avatar"}}}}}], "is_critical_group": true}, "mid": "649919349"}}, "content": {"message": "\u90fd\u5dee\u4e0d\u591a", "members": [], "jump_url": {}, "max_line": 6}, "replies": null, "assist": 0, "up_action": {"like": false, "reply": false}, "invisible": false, "reply_control": {"max_line": 6, "time_desc": "1\u5c0f\u65f6\u524d\u53d1\u5e03"}, "folder": {"has_folded": false, "is_folded": false, "rule": ""}, "dynamic_id_str": "0", "note_cvid_str": "0", "track_info": ""}], "assist": 0, "up_action": {"like": false, "reply": false}, "invisible": false, "reply_control": {"max_line": 6, "sub_reply_entry_text": "\u51711\u6761\u56de\u590d", "sub_reply_title_text": "\u76f8\u5173\u56de\u590d\u51711\u6761", "time_desc": "5\u5c0f\u65f6\u524d\u53d1\u5e03"}, "folder": {"has_folded": false, "is_folded": false, "rule": ""}, "dynamic_id_str": "0", "note_cvid_str": "0", "track_info": ""}, {"rpid": 230612575456, "oid": 1156233854, "type": 1, "mid": 93846797, "root": 0, "parent": 0, "dialog": 0, "count": 0, "rcount": 0, "state": 0, "fansgrade": 0, "attr": 0, "ctime": 1720576314, "mid_str": "93846797", "oid_str": "1156233854", "rpid_str": "230612575456", "root_str": "0", "parent_str": "0", "dialog_str": "0", "like": 0, "action": 0, "member": {"mid": "93846797", "uname": "\u4ece\u6765\u4e0d\u68a6\u60f3\u7684\u51e1", "sex": "\u7537", "sign": "\u521d\u5fc3\u6613\u5f97\u59cb\u7ec8\u96be\u5b88", "avatar": "http://i2.hdslb.com/bfs/face/724293fd052ebfab721c76f992aa42f73feb3f6e.jpg", "rank": "10000", "face_nft_new": 0, "is_senior_member": 0, "senior": {}, "level_info": {"current_level": 6, "current_min": 0, "current_exp": 0, "next_exp": 0}, "pendant": {"pid": 0, "name": "", "image": "", "expire": 0, "image_enhance": "", "image_enhance_frame": "", "n_pid": 0}, "nameplate": {"nid": 0, "name": "", "image": "", "image_small": "", "level": "", "condition": ""}, "official_verify": {"type": -1, "desc": ""}, "vip": {"vipType": 0, "vipDueDate": 0, "dueRemark": "", "accessStatus": 0, "vipStatus": 0, "vipStatusWarn": "", "themeType": 0, "label": {"path": "", "text": "", "label_theme": "", "text_color": "", "bg_style": 0, "bg_color": "", "border_color": "", "use_img_label": true, "img_label_uri_hans": "", "img_label_uri_hant": "", "img_label_uri_hans_static": "https://i0.hdslb.com/bfs/vip/d7b702ef65a976b20ed854cbd04cb9e27341bb79.png", "img_label_uri_hant_static": "https://i0.hdslb.com/bfs/activity-plat/static/20220614/e369244d0b14644f5e1a06431e22a4d5/KJunwh19T5.png"}, "avatar_subscript": 0, "nickname_color": ""}, "fans_detail": null, "user_sailing": null, "is_contractor": false, "contract_desc": "", "nft_interaction": null, "avatar_item": {"container_size": {"width": 1.8, "height": 1.8}, "fallback_layers": {"layers": [{"visible": true, "general_spec": {"pos_spec": {"coordinate_pos": 2, "axis_x": 0.9, "axis_y": 0.9}, "size_spec": {"width": 1, "height": 1}, "render_spec": {"opacity": 1}}, "layer_config": {"tags": {"AVATAR_LAYER": {}, "GENERAL_CFG": {"config_type": 1, "general_config": {"web_css_style": {"borderRadius": "50%"}}}}, "is_critical": true}, "resource": {"res_type": 3, "res_image": {"image_src": {"src_type": 1, "placeholder": 6, "remote": {"url": "http://i2.hdslb.com/bfs/face/724293fd052ebfab721c76f992aa42f73feb3f6e.jpg", "bfs_style": "widget-layer-avatar"}}}}}], "is_critical_group": true}, "mid": "93846797"}}, "content": {"message": "\u4ed6\u4e0d\u5728\u4e86", "members": [], "jump_url": {}, "max_line": 6}, "replies": [], "assist": 0, "up_action": {"like": false, "reply": false}, "invisible": false, "reply_control": {"max_line": 6, "time_desc": "5\u5c0f\u65f6\u524d\u53d1\u5e03"}, "folder": {"has_folded": false, "is_folded": false, "rule": ""}, "dynamic_id_str": "0", "note_cvid_str": "0", "track_info": ""}, {"rpid": 230608650368, "oid": 1156233854, "type": 1, "mid": 2147385863, "root": 0, "parent": 0, "dialog": 0, "count": 0, "rcount": 0, "state": 0, "fansgrade": 0, "attr": 0, "ctime": 1720574339, "mid_str": "2147385863", "oid_str": "1156233854", "rpid_str": "230608650368", "root_str": "0", "parent_str": "0", "dialog_str": "0", "like": 0, "action": 0, "member": {"mid": "2147385863", "uname": "ACE\u90ac\u5343\u4e07", "sex": "\u7537", "sign": "\u8fd8\u8bb0\u5f97\u6211\u4eec\u600e\u4e48\u8ba4\u8bc6\u7684\u5417\uff1f", "avatar": "https://i2.hdslb.com/bfs/face/1bc4a8a3ba9a449c157699a5258ccde82388baa4.jpg", "rank": "10000", "face_nft_new": 0, "is_senior_member": 1, "senior": {"status": 2}, "level_info": {"current_level": 6, "current_min": 0, "current_exp": 0, "next_exp": 0}, "pendant": {"pid": 4613, "name": "\u6a58\u732b\u6302\u4ef6", "image": "https://i2.hdslb.com/bfs/garb/item/e90b968cef3e268bdb33efb5052ae9ebbf745628.png", "expire": 0, "image_enhance": "https://i2.hdslb.com/bfs/garb/item/e6d8473af8badd6e9888d1f7b0c1fea6855c5665.webp", "image_enhance_frame": "https://i2.hdslb.com/bfs/garb/item/4882dcaa14650c1f476894e63e02c023692e66bb.png", "n_pid": 4613}, "nameplate": {"nid": 8, "name": "\u77e5\u540d\u5076\u50cf", "image": "https://i0.hdslb.com/bfs/face/27a952195555e64508310e366b3e38bd4cd143fc.png", "image_small": "https://i0.hdslb.com/bfs/face/0497be49e08357bf05bca56e33a0637a273a7610.png", "level": "\u7a00\u6709\u52cb\u7ae0", "condition": "\u6240\u6709\u81ea\u5236\u89c6\u9891\u603b\u64ad\u653e\u6570>=100\u4e07"}, "official_verify": {"type": -1, "desc": ""}, "vip": {"vipType": 2, "vipDueDate": 1862064000000, "dueRemark": "", "accessStatus": 0, "vipStatus": 1, "vipStatusWarn": "", "themeType": 0, "label": {"path": "", "text": "\u5e74\u5ea6\u5927\u4f1a\u5458", "label_theme": "annual_vip", "text_color": "#FFFFFF", "bg_style": 1, "bg_color": "#FB7299", "border_color": "", "use_img_label": true, "img_label_uri_hans": "", "img_label_uri_hant": "", "img_label_uri_hans_static": "https://i0.hdslb.com/bfs/vip/8d4f8bfc713826a5412a0a27eaaac4d6b9ede1d9.png", "img_label_uri_hant_static": "https://i0.hdslb.com/bfs/activity-plat/static/20220614/e369244d0b14644f5e1a06431e22a4d5/VEW8fCC0hg.png"}, "avatar_subscript": 1, "nickname_color": "#FB7299"}, "fans_detail": null, "user_sailing": {"pendant": {"id": 4613, "name": "\u6a58\u732b\u6302\u4ef6", "image": "https://i0.hdslb.com/bfs/garb/item/e90b968cef3e268bdb33efb5052ae9ebbf745628.png", "jump_url": "", "type": "pay", "image_enhance": "https://i0.hdslb.com/bfs/garb/item/e6d8473af8badd6e9888d1f7b0c1fea6855c5665.webp", "image_enhance_frame": "https://i0.hdslb.com/bfs/garb/item/4882dcaa14650c1f476894e63e02c023692e66bb.png"}, "cardbg": {"id": 60622, "name": "\u5c0f\u6797\u5bb6\u7684\u9f99\u5973\u4ec6S", "image": "http://i0.hdslb.com/bfs/archive/e902a9b89b3c3f7ce9431995419a0884671cd64c.png", "jump_url": "https://www.bilibili.com/h5/mall/digital-card/home?act_id=226&from=reply&f_source=garb&-Abrowser=live&hybrid_set_header=2&navhide=1&anchor_task=1", "fan": {"is_fan": 1, "number": 703, "color": "#BFC8D2", "name": "", "num_desc": "000703", "num_prefix": "CD.", "color_format": {"start_point": "0,0", "end_point": "100,100", "colors": ["#B8C7D0FF", "#A2A7B0FF"], "gradients": [0, 100]}}, "type": "collect_card", "image_group": null}, "cardbg_with_focus": null}, "user_sailing_v2": {"pendant": {"id": 4613, "name": "\u6a58\u732b\u6302\u4ef6", "image": "https://i0.hdslb.com/bfs/garb/item/e90b968cef3e268bdb33efb5052ae9ebbf745628.png", "type": "pay", "image_enhance": "https://i0.hdslb.com/bfs/garb/item/e6d8473af8badd6e9888d1f7b0c1fea6855c5665.webp", "image_enhance_frame": "https://i0.hdslb.com/bfs/garb/item/4882dcaa14650c1f476894e63e02c023692e66bb.png"}, "card_bg": {"id": 60622, "name": "\u5c0f\u6797\u5bb6\u7684\u9f99\u5973\u4ec6S", "image": "http://i0.hdslb.com/bfs/archive/e902a9b89b3c3f7ce9431995419a0884671cd64c.png", "jump_url": "https://www.bilibili.com/h5/mall/digital-card/home?act_id=226&from=reply&f_source=garb&-Abrowser=live&hybrid_set_header=2&navhide=1&anchor_task=1", "fan": {"is_fan": 1, "number": 703, "color": "#BFC8D2", "num_desc": "000703", "num_prefix": "CD.", "color_format": {"start_point": "0,0", "end_point": "100,100", "colors": ["#B8C7D0FF", "#A2A7B0FF"], "gradients": [0, 100]}}, "type": "collect_card"}}, "is_contractor": false, "contract_desc": "", "nft_interaction": null, "avatar_item": {"container_size": {"width": 1.8, "height": 1.8}, "layers": [{"layers": [{"visible": true, "general_spec": {"pos_spec": {"coordinate_pos": 2, "axis_x": 0.9, "axis_y": 0.9}, "size_spec": {"width": 0.787, "height": 0.787}, "render_spec": {"opacity": 1}}, "layer_config": {"tags": {"AVATAR_LAYER": {}, "GENERAL_CFG": {"config_type": 1, "general_config": {"web_css_style": {"borderRadius": "50%"}}}}, "is_critical": true}, "resource": {"res_type": 3, "res_image": {"image_src": {"src_type": 1, "placeholder": 6, "remote": {"url": "https://i2.hdslb.com/bfs/face/1bc4a8a3ba9a449c157699a5258ccde82388baa4.jpg", "bfs_style": "widget-layer-avatar"}}}}}], "is_critical_group": true}, {"layers": [{"visible": true, "general_spec": {"pos_spec": {"coordinate_pos": 2, "axis_x": 0.9, "axis_y": 0.9}, "size_spec": {"width": 1.375, "height": 1.375}, "render_spec": {"opacity": 1}}, "layer_config": {"tags": {"PENDENT_LAYER": {}}}, "resource": {"res_type": 4, "res_animation": {"webp_src": {"src_type": 1, "remote": {"url": "https://i2.hdslb.com/bfs/garb/item/e6d8473af8badd6e9888d1f7b0c1fea6855c5665.webp", "bfs_style": "widget-layer-avatar"}}}}}]}, {"layers": [{"visible": true, "general_spec": {"pos_spec": {"coordinate_pos": 1, "axis_x": 0.9685, "axis_y": 0.9851666666666666}, "size_spec": {"width": 0.41666666666666663, "height": 0.41666666666666663}, "render_spec": {"opacity": 1}}, "layer_config": {"tags": {"GENERAL_CFG": {"config_type": 1, "general_config": {"web_css_style": {"background-color": "rgb(255,255,255)", "border": "2px solid rgba(255,255,255,1)", "borderRadius": "50%", "boxSizing": "border-box"}}}, "ICON_LAYER": {}}}, "resource": {"res_type": 3, "res_image": {"image_src": {"src_type": 2, "local": 1}}}}]}], "fallback_layers": {"layers": [{"visible": true, "general_spec": {"pos_spec": {"coordinate_pos": 2, "axis_x": 0.9, "axis_y": 0.9}, "size_spec": {"width": 0.787, "height": 0.787}, "render_spec": {"opacity": 1}}, "layer_config": {"tags": {"AVATAR_LAYER": {}, "GENERAL_CFG": {"config_type": 1, "general_config": {"web_css_style": {"borderRadius": "50%"}}}}, "is_critical": true}, "resource": {"res_type": 3, "res_image": {"image_src": {"src_type": 1, "placeholder": 6, "remote": {"url": "https://i2.hdslb.com/bfs/face/1bc4a8a3ba9a449c157699a5258ccde82388baa4.jpg", "bfs_style": "widget-layer-avatar"}}}}}, {"visible": true, "general_spec": {"pos_spec": {"coordinate_pos": 2, "axis_x": 0.9, "axis_y": 0.9}, "size_spec": {"width": 1.375, "height": 1.375}, "render_spec": {"opacity": 1}}, "layer_config": {"tags": {"PENDENT_LAYER": {}}}, "resource": {"res_type": 3, "res_image": {"image_src": {"src_type": 1, "remote": {"url": "https://i2.hdslb.com/bfs/garb/item/e90b968cef3e268bdb33efb5052ae9ebbf745628.png", "bfs_style": "widget-layer-avatar"}}}}}, {"visible": true, "general_spec": {"pos_spec": {"coordinate_pos": 1, "axis_x": 0.9685, "axis_y": 0.9851666666666666}, "size_spec": {"width": 0.41666666666666663, "height": 0.41666666666666663}, "render_spec": {"opacity": 1}}, "layer_config": {"tags": {"GENERAL_CFG": {"config_type": 1, "general_config": {"web_css_style": {"background-color": "rgb(255,255,255)", "border": "2px solid rgba(255,255,255,1)", "borderRadius": "50%", "boxSizing": "border-box"}}}, "ICON_LAYER": {}}}, "resource": {"res_type": 3, "res_image": {"image_src": {"src_type": 2, "local": 1}}}}], "is_critical_group": true}, "mid": "2147385863"}}, "content": {"message": "\u6211\u5bb6\u4ee5\u524d\u8fc7\u5e74\u7684\u65f6\u5019\u7089\u5b50\u70e7\u4e0d\u8fc7\u6765\uff0c\u5c31\u62ff\u8fd9\u4e2a\u4e00\u6837\u7684\u58f6\u653e\u5230\u5916\u9762\u70e7\u6c34[\u7b11\u54ed]", "members": [], "emote": {"[\u7b11\u54ed]": {"id": 509, "package_id": 1, "state": 0, "type": 1, "attr": 0, "text": "[\u7b11\u54ed]", "url": "https://i0.hdslb.com/bfs/emote/c3043ba94babf824dea03ce500d0e73763bf4f40.png", "meta": {"size": 1, "suggest": [""]}, "mtime": 1668688325, "jump_title": "\u7b11\u54ed"}}, "jump_url": {}, "max_line": 6}, "replies": [], "assist": 0, "up_action": {"like": false, "reply": false}, "invisible": false, "reply_control": {"max_line": 6, "time_desc": "6\u5c0f\u65f6\u524d\u53d1\u5e03"}, "folder": {"has_folded": false, "is_folded": false, "rule": ""}, "dynamic_id_str": "0", "note_cvid_str": "0", "track_info": ""}, {"rpid": 230594147040, "oid": 1156233854, "type": 1, "mid": 474621486, "root": 0, "parent": 0, "dialog": 0, "count": 0, "rcount": 0, "state": 0, "fansgrade": 0, "attr": 0, "ctime": 1720561271, "mid_str": "474621486", "oid_str": "1156233854", "rpid_str": "230594147040", "root_str": "0", "parent_str": "0", "dialog_str": "0", "like": 0, "action": 0, "member": {"mid": "474621486", "uname": "\u6545\u4eba\u7e41\u82b1\u5fc6\u7ae5\u5e74", "sex": "\u4fdd\u5bc6", "sign": " \u7ea2\u989c\u76f8\u601d\u82e6\uff0c\u51e0\u756a\u96be\u76f8\u4ed8\u3002\u5341\u5e74\u76f8\u601d\u767e\u5e74\u6e21\uff0c\u4e0d\u65a9\u76f8\u601d\u5316\u6210\u6545\uff0c\u68a6\u5fc6\u6dfc\uff0c\u83ab\u56de\u590d\uff01", "avatar": "https://i0.hdslb.com/bfs/face/81a98db2fc5ba02b024ed4a052e49d664e6be57b.jpg", "rank": "10000", "face_nft_new": 0, "is_senior_member": 0, "senior": {}, "level_info": {"current_level": 5, "current_min": 0, "current_exp": 0, "next_exp": 0}, "pendant": {"pid": 994, "name": "\u683c\u5170\u82ac\u591a", "image": "https://i0.hdslb.com/bfs/face/2dee633139ce7c6b0dca657236240cc399c090be.png", "expire": 0, "image_enhance": "https://i0.hdslb.com/bfs/face/2dee633139ce7c6b0dca657236240cc399c090be.png", "image_enhance_frame": "", "n_pid": 994}, "nameplate": {"nid": 0, "name": "", "image": "", "image_small": "", "level": "", "condition": ""}, "official_verify": {"type": -1, "desc": ""}, "vip": {"vipType": 2, "vipDueDate": 1722009600000, "dueRemark": "", "accessStatus": 0, "vipStatus": 1, "vipStatusWarn": "", "themeType": 0, "label": {"path": "", "text": "\u5e74\u5ea6\u5927\u4f1a\u5458", "label_theme": "annual_vip", "text_color": "#FFFFFF", "bg_style": 1, "bg_color": "#FB7299", "border_color": "", "use_img_label": true, "img_label_uri_hans": "", "img_label_uri_hant": "", "img_label_uri_hans_static": "https://i0.hdslb.com/bfs/vip/8d4f8bfc713826a5412a0a27eaaac4d6b9ede1d9.png", "img_label_uri_hant_static": "https://i0.hdslb.com/bfs/activity-plat/static/20220614/e369244d0b14644f5e1a06431e22a4d5/VEW8fCC0hg.png"}, "avatar_subscript": 1, "nickname_color": "#FB7299"}, "fans_detail": null, "user_sailing": null, "is_contractor": false, "contract_desc": "", "nft_interaction": null, "avatar_item": {"container_size": {"width": 1.8, "height": 1.8}, "fallback_layers": {"layers": [{"visible": true, "general_spec": {"pos_spec": {"coordinate_pos": 2, "axis_x": 0.9, "axis_y": 0.9}, "size_spec": {"width": 0.787, "height": 0.787}, "render_spec": {"opacity": 1}}, "layer_config": {"tags": {"AVATAR_LAYER": {}, "GENERAL_CFG": {"config_type": 1, "general_config": {"web_css_style": {"borderRadius": "50%"}}}}, "is_critical": true}, "resource": {"res_type": 3, "res_image": {"image_src": {"src_type": 1, "placeholder": 6, "remote": {"url": "https://i0.hdslb.com/bfs/face/81a98db2fc5ba02b024ed4a052e49d664e6be57b.jpg", "bfs_style": "widget-layer-avatar"}}}}}, {"visible": true, "general_spec": {"pos_spec": {"coordinate_pos": 2, "axis_x": 0.9, "axis_y": 0.9}, "size_spec": {"width": 1.375, "height": 1.375}, "render_spec": {"opacity": 1}}, "layer_config": {"tags": {"PENDENT_LAYER": {}}}, "resource": {"res_type": 3, "res_image": {"image_src": {"src_type": 1, "remote": {"url": "https://i0.hdslb.com/bfs/face/2dee633139ce7c6b0dca657236240cc399c090be.png", "bfs_style": "widget-layer-avatar"}}}}}, {"visible": true, "general_spec": {"pos_spec": {"coordinate_pos": 1, "axis_x": 0.9685, "axis_y": 0.9851666666666666}, "size_spec": {"width": 0.41666666666666663, "height": 0.41666666666666663}, "render_spec": {"opacity": 1}}, "layer_config": {"tags": {"GENERAL_CFG": {"config_type": 1, "general_config": {"web_css_style": {"background-color": "rgb(255,255,255)", "border": "2px solid rgba(255,255,255,1)", "borderRadius": "50%", "boxSizing": "border-box"}}}, "ICON_LAYER": {}}}, "resource": {"res_type": 3, "res_image": {"image_src": {"src_type": 2, "local": 1}}}}], "is_critical_group": true}, "mid": "474621486"}}, "content": {"message": "\u4e00\u524d\u786e\u5b9e\u6709\u70e7\u5f00\u6c34\u8fd9\u4e2a\u5546\u5e97\uff0c\u6211\u4eec\u8fd9\u8fb9\u53eb\u8001\u864e\u7076\u3002\u5e02\u96c6\u4e0a\u4e13\u95e8\u63d0\u4f9b\u5f00\u6c34\u7684\uff0c\u597d\u50cf\u662f\u4e03\u516b\u5341\u5e74\u4ee3\u7684\u3002", "members": [], "jump_url": {}, "max_line": 6}, "replies": [], "assist": 0, "up_action": {"like": false, "reply": false}, "invisible": false, "reply_control": {"max_line": 6, "time_desc": "9\u5c0f\u65f6\u524d\u53d1\u5e03"}, "folder": {"has_folded": false, "is_folded": false, "rule": ""}, "dynamic_id_str": "0", "note_cvid_str": "0", "track_info": ""}, {"rpid": 230591352320, "oid": 1156233854, "type": 1, "mid": 3546602169960739, "root": 0, "parent": 0, "dialog": 0, "count": 0, "rcount": 0, "state": 0, "fansgrade": 0, "attr": 0, "ctime": 1720555339, "mid_str": "3546602169960739", "oid_str": "1156233854", "rpid_str": "230591352320", "root_str": "0", "parent_str": "0", "dialog_str": "0", "like": 0, "action": 0, "member": {"mid": "3546602169960739", "uname": "\u5c0f\u5434\u5c0f\u9c7c", "sex": "\u7537", "sign": "\u4e00\u4e2a\u5411\u5f80\u81ea\u7531\u7684boy", "avatar": "https://i1.hdslb.com/bfs/face/919682b8f93a3775079dd7c945c78f5794e14021.jpg", "rank": "10000", "face_nft_new": 0, "is_senior_member": 0, "senior": {}, "level_info": {"current_level": 3, "current_min": 0, "current_exp": 0, "next_exp": 0}, "pendant": {"pid": 0, "name": "", "image": "", "expire": 0, "image_enhance": "", "image_enhance_frame": "", "n_pid": 0}, "nameplate": {"nid": 0, "name": "", "image": "", "image_small": "", "level": "", "condition": ""}, "official_verify": {"type": -1, "desc": ""}, "vip": {"vipType": 0, "vipDueDate": 0, "dueRemark": "", "accessStatus": 0, "vipStatus": 0, "vipStatusWarn": "", "themeType": 0, "label": {"path": "", "text": "", "label_theme": "", "text_color": "", "bg_style": 0, "bg_color": "", "border_color": "", "use_img_label": true, "img_label_uri_hans": "", "img_label_uri_hant": "", "img_label_uri_hans_static": "https://i0.hdslb.com/bfs/vip/d7b702ef65a976b20ed854cbd04cb9e27341bb79.png", "img_label_uri_hant_static": "https://i0.hdslb.com/bfs/activity-plat/static/20220614/e369244d0b14644f5e1a06431e22a4d5/KJunwh19T5.png"}, "avatar_subscript": 0, "nickname_color": ""}, "fans_detail": null, "user_sailing": null, "is_contractor": false, "contract_desc": "", "nft_interaction": null, "avatar_item": {"container_size": {"width": 1.8, "height": 1.8}, "fallback_layers": {"layers": [{"visible": true, "general_spec": {"pos_spec": {"coordinate_pos": 2, "axis_x": 0.9, "axis_y": 0.9}, "size_spec": {"width": 1, "height": 1}, "render_spec": {"opacity": 1}}, "layer_config": {"tags": {"AVATAR_LAYER": {}, "GENERAL_CFG": {"config_type": 1, "general_config": {"web_css_style": {"borderRadius": "50%"}}}}, "is_critical": true}, "resource": {"res_type": 3, "res_image": {"image_src": {"src_type": 1, "placeholder": 6, "remote": {"url": "https://i1.hdslb.com/bfs/face/919682b8f93a3775079dd7c945c78f5794e14021.jpg", "bfs_style": "widget-layer-avatar"}}}}}], "is_critical_group": true}, "mid": "3546602169960739"}}, "content": {"message": "\u4ec0\u4e48\u65f6\u5019\u7684\u89c6\u9891\u4e86\u600e\u4e48\u53c8\u518d\u53d1\u4e00\u904d", "members": [], "jump_url": {}, "max_line": 6}, "replies": [], "assist": 0, "up_action": {"like": false, "reply": false}, "invisible": false, "reply_control": {"max_line": 6, "time_desc": "11\u5c0f\u65f6\u524d\u53d1\u5e03"}, "folder": {"has_folded": false, "is_folded": false, "rule": ""}, "dynamic_id_str": "0", "note_cvid_str": "0", "track_info": ""}, {"rpid": 230589579792, "oid": 1156233854, "type": 1, "mid": 624801932, "root": 0, "parent": 0, "dialog": 0, "count": 0, "rcount": 0, "state": 0, "fansgrade": 0, "attr": 0, "ctime": 1720552245, "mid_str": "624801932", "oid_str": "1156233854", "rpid_str": "230589579792", "root_str": "0", "parent_str": "0", "dialog_str": "0", "like": 0, "action": 0, "member": {"mid": "624801932", "uname": "\u52a0\u6cb9\u5e03\u5170\u767b", "sex": "\u4fdd\u5bc6", "sign": "", "avatar": "https://i0.hdslb.com/bfs/face/member/noface.jpg", "rank": "10000", "face_nft_new": 0, "is_senior_member": 0, "senior": {}, "level_info": {"current_level": 3, "current_min": 0, "current_exp": 0, "next_exp": 0}, "pendant": {"pid": 0, "name": "", "image": "", "expire": 0, "image_enhance": "", "image_enhance_frame": "", "n_pid": 0}, "nameplate": {"nid": 0, "name": "", "image": "", "image_small": "", "level": "", "condition": ""}, "official_verify": {"type": -1, "desc": ""}, "vip": {"vipType": 0, "vipDueDate": 0, "dueRemark": "", "accessStatus": 0, "vipStatus": 0, "vipStatusWarn": "", "themeType": 0, "label": {"path": "", "text": "", "label_theme": "", "text_color": "", "bg_style": 0, "bg_color": "", "border_color": "", "use_img_label": true, "img_label_uri_hans": "", "img_label_uri_hant": "", "img_label_uri_hans_static": "https://i0.hdslb.com/bfs/vip/d7b702ef65a976b20ed854cbd04cb9e27341bb79.png", "img_label_uri_hant_static": "https://i0.hdslb.com/bfs/activity-plat/static/20220614/e369244d0b14644f5e1a06431e22a4d5/KJunwh19T5.png"}, "avatar_subscript": 0, "nickname_color": ""}, "fans_detail": null, "user_sailing": null, "is_contractor": false, "contract_desc": "", "nft_interaction": null, "avatar_item": {"container_size": {"width": 1.8, "height": 1.8}, "fallback_layers": {"layers": [{"visible": true, "general_spec": {"pos_spec": {"coordinate_pos": 2, "axis_x": 0.9, "axis_y": 0.9}, "size_spec": {"width": 1, "height": 1}, "render_spec": {"opacity": 1}}, "layer_config": {"tags": {"AVATAR_LAYER": {}, "GENERAL_CFG": {"config_type": 1, "general_config": {"web_css_style": {"borderRadius": "50%"}}}}, "is_critical": true}, "resource": {"res_type": 3, "res_image": {"image_src": {"src_type": 1, "placeholder": 6, "remote": {"url": "https://i0.hdslb.com/bfs/face/member/noface.jpg", "bfs_style": "widget-layer-avatar"}}}}}], "is_critical_group": true}, "mid": "624801932"}}, "content": {"message": "\u201c\u6211\u656c\u5979\uff0c\u5979\u5c31\u7231\u6211\u201d\u2014\u2014\u9707\u8033\u6b32\u804b", "members": [], "jump_url": {"\u6211\u656c\u5979\uff0c\u5979\u5c31\u7231\u6211": {"title": "\u6211\u656c\u5979\uff0c\u5979\u5c31\u7231\u6211", "state": 0, "prefix_icon": "https://i0.hdslb.com/bfs/reply/9f3ad0659e84c96a711b88dd33f4bc2e945045e0.png", "app_url_schema": "bilibili://search?from=appcommentline_search&search_from_source=appcommentline_search&direct_return=true&keyword=%E6%88%91%E6%95%AC%E5%A5%B9%EF%BC%8C%E5%A5%B9%E5%B0%B1%E7%88%B1%E6%88%91&seid=7004122714792251788", "app_name": "", "app_package_name": "", "click_report": "", "is_half_screen": false, "exposure_report": "", "extra": {"goods_show_type": 0, "is_word_search": true, "goods_cm_control": 0, "goods_click_report": "", "goods_exposure_report": ""}, "underline": false, "match_once": true, "pc_url": "//search.bilibili.com/all?from_source=webcommentline_search&keyword=%E6%88%91%E6%95%AC%E5%A5%B9%EF%BC%8C%E5%A5%B9%E5%B0%B1%E7%88%B1%E6%88%91&seid=7004122714792251788", "icon_position": 1}}, "max_line": 6}, "replies": [], "assist": 0, "up_action": {"like": false, "reply": false}, "invisible": false, "reply_control": {"max_line": 6, "time_desc": "12\u5c0f\u65f6\u524d\u53d1\u5e03"}, "folder": {"has_folded": false, "is_folded": false, "rule": ""}, "dynamic_id_str": "0", "note_cvid_str": "0", "track_info": ""}, {"rpid": 230586033232, "oid": 1156233854, "type": 1, "mid": 114071472, "root": 0, "parent": 0, "dialog": 0, "count": 0, "rcount": 0, "state": 0, "fansgrade": 0, "attr": 0, "ctime": 1720548531, "mid_str": "114071472", "oid_str": "1156233854", "rpid_str": "230586033232", "root_str": "0", "parent_str": "0", "dialog_str": "0", "like": 0, "action": 0, "member": {"mid": "114071472", "uname": "\u54cd\u6f6e\u957f\u79bb", "sex": "\u4fdd\u5bc6", "sign": "\u541b\u5b50\u751f\u975e\u5f02\u4e5f\uff0c\u5584\u5047\u4e8e\u7269\u4e5f\u3002", "avatar": "https://i0.hdslb.com/bfs/face/c399e28db35924acd8dab97bd4daf0a2c85ab6cf.jpg", "rank": "10000", "face_nft_new": 0, "is_senior_member": 0, "senior": {}, "level_info": {"current_level": 6, "current_min": 0, "current_exp": 0, "next_exp": 0}, "pendant": {"pid": 4514, "name": "\u840c\u5ba0\u5c0f\u72d7", "image": "https://i0.hdslb.com/bfs/garb/item/28ac49d65a24fd9adc4859061ac4e22f45c8fa0f.png", "expire": 0, "image_enhance": "https://i0.hdslb.com/bfs/garb/item/28ac49d65a24fd9adc4859061ac4e22f45c8fa0f.png", "image_enhance_frame": "", "n_pid": 4514}, "nameplate": {"nid": 60, "name": "\u6709\u7231\u840c\u65b0", "image": "https://i2.hdslb.com/bfs/face/51ca16136e570938450bca360f28761ceb609f33.png", "image_small": "https://i0.hdslb.com/bfs/face/9abfa4769357f85937782c2dbc40fafda4f57217.png", "level": "\u666e\u901a\u52cb\u7ae0", "condition": "\u5f53\u524d\u6301\u6709\u7c89\u4e1d\u52cb\u7ae0\u6700\u9ad8\u7b49\u7ea7>=5\u7ea7"}, "official_verify": {"type": -1, "desc": ""}, "vip": {"vipType": 0, "vipDueDate": 0, "dueRemark": "", "accessStatus": 0, "vipStatus": 0, "vipStatusWarn": "", "themeType": 0, "label": {"path": "", "text": "", "label_theme": "", "text_color": "", "bg_style": 0, "bg_color": "", "border_color": "", "use_img_label": true, "img_label_uri_hans": "", "img_label_uri_hant": "", "img_label_uri_hans_static": "https://i0.hdslb.com/bfs/vip/d7b702ef65a976b20ed854cbd04cb9e27341bb79.png", "img_label_uri_hant_static": "https://i0.hdslb.com/bfs/activity-plat/static/20220614/e369244d0b14644f5e1a06431e22a4d5/KJunwh19T5.png"}, "avatar_subscript": 0, "nickname_color": ""}, "fans_detail": null, "user_sailing": {"pendant": {"id": 4514, "name": "\u840c\u5ba0\u5c0f\u72d7", "image": "https://i0.hdslb.com/bfs/garb/item/28ac49d65a24fd9adc4859061ac4e22f45c8fa0f.png", "jump_url": "", "type": "pay", "image_enhance": "https://i0.hdslb.com/bfs/garb/item/28ac49d65a24fd9adc4859061ac4e22f45c8fa0f.png", "image_enhance_frame": ""}, "cardbg": {"id": 32910, "name": "\u840c\u5ba0\u5c0f\u718a", "image": "https://i0.hdslb.com/bfs/garb/item/37763f33d4eaa01dbb6a9a35865751f47d749a50.png", "jump_url": "https://www.bilibili.com/h5/mall/equity-link/collect-home?item_id=32910&isdiy=0&part=card_bg&from=reply&f_source=garb&vmid=114071472&native.theme=1&navhide=1", "fan": {"is_fan": 1, "number": 4624, "color": "#db8d47", "name": "\u840c\u5ba0\u5c0f\u718a", "num_desc": "004624", "num_prefix": "NO.", "color_format": {"start_point": "0,0", "end_point": "0,100", "colors": ["#db8d47FF", "#db8d47FF"], "gradients": [0, 100]}}, "type": "suit", "image_group": null}, "cardbg_with_focus": null}, "user_sailing_v2": {"pendant": {"id": 4514, "name": "\u840c\u5ba0\u5c0f\u72d7", "image": "https://i0.hdslb.com/bfs/garb/item/28ac49d65a24fd9adc4859061ac4e22f45c8fa0f.png", "type": "pay", "image_enhance": "https://i0.hdslb.com/bfs/garb/item/28ac49d65a24fd9adc4859061ac4e22f45c8fa0f.png"}, "card_bg": {"id": 32910, "name": "\u840c\u5ba0\u5c0f\u718a", "image": "https://i0.hdslb.com/bfs/garb/item/37763f33d4eaa01dbb6a9a35865751f47d749a50.png", "jump_url": "https://www.bilibili.com/h5/mall/equity-link/collect-home?item_id=32910&isdiy=0&part=card_bg&from=reply&f_source=garb&vmid=114071472&native.theme=1&navhide=1", "fan": {"is_fan": 1, "number": 4624, "color": "#db8d47", "name": "\u840c\u5ba0\u5c0f\u718a", "num_desc": "004624", "num_prefix": "NO.", "color_format": {"start_point": "0,0", "end_point": "0,100", "colors": ["#db8d47FF", "#db8d47FF"], "gradients": [0, 100]}}, "type": "suit"}}, "is_contractor": false, "contract_desc": "", "nft_interaction": null, "avatar_item": {"container_size": {"width": 1.8, "height": 1.8}, "fallback_layers": {"layers": [{"visible": true, "general_spec": {"pos_spec": {"coordinate_pos": 2, "axis_x": 0.9, "axis_y": 0.9}, "size_spec": {"width": 0.787, "height": 0.787}, "render_spec": {"opacity": 1}}, "layer_config": {"tags": {"AVATAR_LAYER": {}, "GENERAL_CFG": {"config_type": 1, "general_config": {"web_css_style": {"borderRadius": "50%"}}}}, "is_critical": true}, "resource": {"res_type": 3, "res_image": {"image_src": {"src_type": 1, "placeholder": 6, "remote": {"url": "https://i0.hdslb.com/bfs/face/c399e28db35924acd8dab97bd4daf0a2c85ab6cf.jpg", "bfs_style": "widget-layer-avatar"}}}}}, {"visible": true, "general_spec": {"pos_spec": {"coordinate_pos": 2, "axis_x": 0.9, "axis_y": 0.9}, "size_spec": {"width": 1.375, "height": 1.375}, "render_spec": {"opacity": 1}}, "layer_config": {"tags": {"PENDENT_LAYER": {}}}, "resource": {"res_type": 3, "res_image": {"image_src": {"src_type": 1, "remote": {"url": "https://i0.hdslb.com/bfs/garb/item/28ac49d65a24fd9adc4859061ac4e22f45c8fa0f.png", "bfs_style": "widget-layer-avatar"}}}}}], "is_critical_group": true}, "mid": "114071472"}}, "content": {"message": "\u8fd9\u79cd\u58f6\u53eb\u70e7\u5fc3\u58f6\uff0c\u6211\u5c0f\u65f6\u5019\u5c31\u7528\u8fd9\u79cd\u58f6\u70e7\u6c34\uff0c\u70e7\u51fa\u6765\u7684\u6c34\u4f1a\u6709\u4e00\u80a1\u70df\u5473", "members": [], "jump_url": {}, "max_line": 6}, "replies": [], "assist": 0, "up_action": {"like": false, "reply": false}, "invisible": false, "reply_control": {"max_line": 6, "time_desc": "13\u5c0f\u65f6\u524d\u53d1\u5e03"}, "folder": {"has_folded": false, "is_folded": false, "rule": ""}, "dynamic_id_str": "0", "note_cvid_str": "0", "track_info": ""}, {"rpid": 230585764720, "oid": 1156233854, "type": 1, "mid": 21800785, "root": 0, "parent": 0, "dialog": 0, "count": 0, "rcount": 0, "state": 0, "fansgrade": 0, "attr": 0, "ctime": 1720548299, "mid_str": "21800785", "oid_str": "1156233854", "rpid_str": "230585764720", "root_str": "0", "parent_str": "0", "dialog_str": "0", "like": 0, "action": 0, "member": {"mid": "21800785", "uname": "\u6d1bchang\u5b89", "sex": "\u7537", "sign": "", "avatar": "https://i1.hdslb.com/bfs/face/0e6a079563731b03bfdb397d50028b4531937d0e.jpg", "rank": "10000", "face_nft_new": 0, "is_senior_member": 0, "senior": {}, "level_info": {"current_level": 6, "current_min": 0, "current_exp": 0, "next_exp": 0}, "pendant": {"pid": 0, "name": "", "image": "", "expire": 0, "image_enhance": "", "image_enhance_frame": "", "n_pid": 0}, "nameplate": {"nid": 9, "name": "\u51fa\u9053\u5076\u50cf", "image": "https://i2.hdslb.com/bfs/face/3f2d64f048b39fb6c26f3db39df47e6080ec0f9c.png", "image_small": "https://i0.hdslb.com/bfs/face/90c35d41d8a19b19474d6bac672394c17b444ce8.png", "level": "\u9ad8\u7ea7\u52cb\u7ae0", "condition": "\u6240\u6709\u81ea\u5236\u89c6\u9891\u603b\u64ad\u653e\u6570>=50\u4e07"}, "official_verify": {"type": -1, "desc": ""}, "vip": {"vipType": 2, "vipDueDate": 1745251200000, "dueRemark": "", "accessStatus": 0, "vipStatus": 1, "vipStatusWarn": "", "themeType": 0, "label": {"path": "", "text": "\u5e74\u5ea6\u5927\u4f1a\u5458", "label_theme": "annual_vip", "text_color": "#FFFFFF", "bg_style": 1, "bg_color": "#FB7299", "border_color": "", "use_img_label": true, "img_label_uri_hans": "", "img_label_uri_hant": "", "img_label_uri_hans_static": "https://i0.hdslb.com/bfs/vip/8d4f8bfc713826a5412a0a27eaaac4d6b9ede1d9.png", "img_label_uri_hant_static": "https://i0.hdslb.com/bfs/activity-plat/static/20220614/e369244d0b14644f5e1a06431e22a4d5/VEW8fCC0hg.png"}, "avatar_subscript": 1, "nickname_color": "#FB7299"}, "fans_detail": null, "user_sailing": null, "is_contractor": false, "contract_desc": "", "nft_interaction": null, "avatar_item": {"container_size": {"width": 1.8, "height": 1.8}, "fallback_layers": {"layers": [{"visible": true, "general_spec": {"pos_spec": {"coordinate_pos": 2, "axis_x": 0.9, "axis_y": 0.9}, "size_spec": {"width": 1, "height": 1}, "render_spec": {"opacity": 1}}, "layer_config": {"tags": {"AVATAR_LAYER": {}, "GENERAL_CFG": {"config_type": 1, "general_config": {"web_css_style": {"borderRadius": "50%"}}}}, "is_critical": true}, "resource": {"res_type": 3, "res_image": {"image_src": {"src_type": 1, "placeholder": 6, "remote": {"url": "https://i1.hdslb.com/bfs/face/0e6a079563731b03bfdb397d50028b4531937d0e.jpg", "bfs_style": "widget-layer-avatar"}}}}}, {"visible": true, "general_spec": {"pos_spec": {"coordinate_pos": 1, "axis_x": 1.025, "axis_y": 1.025}, "size_spec": {"width": 0.41666666666666663, "height": 0.41666666666666663}, "render_spec": {"opacity": 1}}, "layer_config": {"tags": {"GENERAL_CFG": {"config_type": 1, "general_config": {"web_css_style": {"background-color": "rgb(255,255,255)", "border": "2px solid rgba(255,255,255,1)", "borderRadius": "50%", "boxSizing": "border-box"}}}, "ICON_LAYER": {}}}, "resource": {"res_type": 3, "res_image": {"image_src": {"src_type": 2, "local": 1}}}}], "is_critical_group": true}, "mid": "21800785"}}, "content": {"message": "\u60f3\u5230\u6211\u7237\u7237\u4e86\uff0c\u6211\u7237\u7237\u6bd4\u8fd9\u4e2a\u7237\u7237\u5927\u4e00\u4e9b\u9a6c\u4e0a\u4e5d\u5341\u4e86\u3002\u4e5f\u662f\u8d76\u4e86\u4e00\u8f88\u96c6\uff0c\u5356\u8863\u670d\uff0c22\u5e74\u8fd8\u5728\u51fa\u644a\u3002\u4e00\u4e2a\u4eba\u6491\u8d77\u4e86\u4e24\u5927\u5bb6\u5b50\u4eba\uff0c\u6211\u5976\u597621\u5e74\u8fd8\u8ddf\u7740\u4e00\u8d77\u53bb\u8d76\u96c6\uff0c\u540e\u6765\u9aa8\u5934\u592a\u8106\u4e86\u5bb9\u6613\u9aa8\u6298\u5c31\u4e0d\u518d\u8ddf\u7740\u4e86\u3002\u518d\u540e\u6765\u75ab\u60c5\u653e\u5f00\uff0c\u7237\u7237\u611f\u67d3\u4e86\uff0c\u8eab\u4f53\u72b6\u6001\u6162\u6162\u5c31\u4e0b\u6ed1\u4e86\uff0c\u7ec8\u4e8e\u4e5f\u542c\u529d\u4e86\u4e0d\u518d\u8d76\u96c6\u4e86\u3002\u6211\u4e5f\u662f\u4e34\u6c82\u7684\uff0c\u5728\u5e02\u91cc\u5de5\u4f5c\u5fd9\u7684\u8981\u6b7b\uff0c\u5f88\u4e45\u6ca1\u56de\u53bb\u770b\u4ed6\u4eec\u4e86\u3002\u7a81\u7136\u60f3\u6211\u7237\u7237\u4e86\uff0c\u4ed6\u8eab\u4f53\u8fd8\u597d\u5c31\u662f\u8033\u6735\u4e0d\u7075\u5149\u4e86\u3002", "members": [], "jump_url": {}, "max_line": 6}, "replies": [], "assist": 0, "up_action": {"like": false, "reply": false}, "invisible": false, "reply_control": {"max_line": 6, "time_desc": "13\u5c0f\u65f6\u524d\u53d1\u5e03"}, "folder": {"has_folded": false, "is_folded": false, "rule": ""}, "dynamic_id_str": "0", "note_cvid_str": "0", "track_info": ""}, {"rpid": 230583905888, "oid": 1156233854, "type": 1, "mid": 2048208649, "root": 0, "parent": 0, "dialog": 0, "count": 0, "rcount": 0, "state": 0, "fansgrade": 0, "attr": 0, "ctime": 1720546870, "mid_str": "2048208649", "oid_str": "1156233854", "rpid_str": "230583905888", "root_str": "0", "parent_str": "0", "dialog_str": "0", "like": 0, "action": 0, "member": {"mid": "2048208649", "uname": "\u4e2d\u56fd\u8d8a\u6765\u8d8a\u597d\u6c14\u6b7b\u4f60-", "sex": "\u7537", "sign": "\u53ea\u8981\u6709\u6211\u4e00\u53e3\u5403\u7684\uff0c\u90a3\u6211\u5c31\u5feb\u4e50\u7684\u6d3b\u7740\u3002", "avatar": "https://i1.hdslb.com/bfs/face/729f958a7a1a14bdc8f4f1fb8362d36716518ded.jpg", "rank": "10000", "face_nft_new": 0, "is_senior_member": 0, "senior": {}, "level_info": {"current_level": 5, "current_min": 0, "current_exp": 0, "next_exp": 0}, "pendant": {"pid": 0, "name": "", "image": "", "expire": 0, "image_enhance": "", "image_enhance_frame": "", "n_pid": 0}, "nameplate": {"nid": 4, "name": "\u9752\u94dc\u6bbf\u5802", "image": "https://i2.hdslb.com/bfs/face/2879cd5fb8518f7c6da75887994c1b2a7fe670bd.png", "image_small": "https://i2.hdslb.com/bfs/face/6707c120e00a3445933308fd9b7bd9fad99e9ec4.png", "level": "\u666e\u901a\u52cb\u7ae0", "condition": "\u5355\u4e2a\u81ea\u5236\u89c6\u9891\u603b\u64ad\u653e\u6570>=1\u4e07"}, "official_verify": {"type": -1, "desc": ""}, "vip": {"vipType": 0, "vipDueDate": 0, "dueRemark": "", "accessStatus": 0, "vipStatus": 0, "vipStatusWarn": "", "themeType": 0, "label": {"path": "", "text": "", "label_theme": "", "text_color": "", "bg_style": 0, "bg_color": "", "border_color": "", "use_img_label": true, "img_label_uri_hans": "", "img_label_uri_hant": "", "img_label_uri_hans_static": "https://i0.hdslb.com/bfs/vip/d7b702ef65a976b20ed854cbd04cb9e27341bb79.png", "img_label_uri_hant_static": "https://i0.hdslb.com/bfs/activity-plat/static/20220614/e369244d0b14644f5e1a06431e22a4d5/KJunwh19T5.png"}, "avatar_subscript": 0, "nickname_color": ""}, "fans_detail": null, "user_sailing": null, "is_contractor": false, "contract_desc": "", "nft_interaction": null, "avatar_item": {"container_size": {"width": 1.8, "height": 1.8}, "fallback_layers": {"layers": [{"visible": true, "general_spec": {"pos_spec": {"coordinate_pos": 2, "axis_x": 0.9, "axis_y": 0.9}, "size_spec": {"width": 1, "height": 1}, "render_spec": {"opacity": 1}}, "layer_config": {"tags": {"AVATAR_LAYER": {}, "GENERAL_CFG": {"config_type": 1, "general_config": {"web_css_style": {"borderRadius": "50%"}}}}, "is_critical": true}, "resource": {"res_type": 3, "res_image": {"image_src": {"src_type": 1, "placeholder": 6, "remote": {"url": "https://i1.hdslb.com/bfs/face/729f958a7a1a14bdc8f4f1fb8362d36716518ded.jpg", "bfs_style": "widget-layer-avatar"}}}}}], "is_critical_group": true}, "mid": "2048208649"}}, "content": {"message": "\u201c\u6211\u656c\u5979\uff0c\u5979\u5c31\u7231\u6211\u3002\u201d\u6211\u662f\u8bd7\u4eba\uff0c\u8fd9\u5c31\u662f\u8bd7\u53e5\u3002", "members": [], "jump_url": {}, "max_line": 6}, "replies": [], "assist": 0, "up_action": {"like": false, "reply": false}, "invisible": false, "reply_control": {"max_line": 6, "time_desc": "13\u5c0f\u65f6\u524d\u53d1\u5e03"}, "folder": {"has_folded": false, "is_folded": false, "rule": ""}, "dynamic_id_str": "0", "note_cvid_str": "0", "track_info": ""}, {"rpid": 230581047424, "oid": 1156233854, "type": 1, "mid": 34859384, "root": 0, "parent": 0, "dialog": 0, "count": 0, "rcount": 0, "state": 0, "fansgrade": 0, "attr": 0, "ctime": 1720545029, "mid_str": "34859384", "oid_str": "1156233854", "rpid_str": "230581047424", "root_str": "0", "parent_str": "0", "dialog_str": "0", "like": 0, "action": 0, "member": {"mid": "34859384", "uname": "\u98d8\u6e3a\u4e09\u5c71\u5916", "sex": "\u7537", "sign": "\u7528\u534e\u4e3a\uff0c\u7a7f\u674e\u5b81\uff0c\u5f00\u6bd4\u4e9a\u8fea\uff0c\u73a9\u539f\u795e\uff0c\u652f\u6301RNG\uff0c\u5076\u50cf\u662f\u4e01\u771f\u73cd\u73e0\uff0c\u5403\u767d\u8c61\uff0c\u7231\u770b\u89c2\u5bdf\u8005\u7f51\uff0c\u559c\u6b22\u7684\u7535\u5f71\u662f\u6218\u72fc\uff0c\u6b22\u8fce\u5fd7\u540c\u9053\u5408\u7684\u4eba\u6765\u548c\u6211\u4ea4\u670b\u53cb\u3002", "avatar": "https://i2.hdslb.com/bfs/face/2d4d25f0a89d3f15e49f8ae3d2c53397c042d421.jpg", "rank": "10000", "face_nft_new": 0, "is_senior_member": 0, "senior": {}, "level_info": {"current_level": 6, "current_min": 0, "current_exp": 0, "next_exp": 0}, "pendant": {"pid": 0, "name": "", "image": "", "expire": 0, "image_enhance": "", "image_enhance_frame": "", "n_pid": 0}, "nameplate": {"nid": 57, "name": "\u6536\u96c6\u840c\u65b0", "image": "https://i1.hdslb.com/bfs/face/7767275600ea63d351b22fa87ec15a79aa24e5e5.png", "image_small": "https://i2.hdslb.com/bfs/face/6589d992655595bf51543f268040eaeaed372fae.png", "level": "\u666e\u901a\u52cb\u7ae0", "condition": "\u540c\u65f6\u62e5\u6709\u7c89\u4e1d\u52cb\u7ae0>=5\u4e2a"}, "official_verify": {"type": -1, "desc": ""}, "vip": {"vipType": 2, "vipDueDate": 1740326400000, "dueRemark": "", "accessStatus": 0, "vipStatus": 1, "vipStatusWarn": "", "themeType": 0, "label": {"path": "", "text": "\u5e74\u5ea6\u5927\u4f1a\u5458", "label_theme": "annual_vip", "text_color": "#FFFFFF", "bg_style": 1, "bg_color": "#FB7299", "border_color": "", "use_img_label": true, "img_label_uri_hans": "", "img_label_uri_hant": "", "img_label_uri_hans_static": "https://i0.hdslb.com/bfs/vip/8d4f8bfc713826a5412a0a27eaaac4d6b9ede1d9.png", "img_label_uri_hant_static": "https://i0.hdslb.com/bfs/activity-plat/static/20220614/e369244d0b14644f5e1a06431e22a4d5/VEW8fCC0hg.png"}, "avatar_subscript": 1, "nickname_color": "#FB7299"}, "fans_detail": null, "user_sailing": {"pendant": null, "cardbg": {"id": 5476, "name": "\u5609\u7136\u4eca\u5929\u5403\u4ec0\u4e48", "image": "https://i0.hdslb.com/bfs/garb/item/4442641bd4001214518a81fa8f790ae7469d3cf7.png", "jump_url": "https://www.bilibili.com/h5/mall/equity-link/collect-home?item_id=5476&isdiy=0&part=card_bg&from=reply&f_source=garb&vmid=34859384&native.theme=1&navhide=1", "fan": {"is_fan": 1, "number": 48994, "color": "#f76a6b", "name": "\u5609\u7136\u4eca\u5929\u5403\u4ec0\u4e48", "num_desc": "048994", "num_prefix": "NO.", "color_format": {"start_point": "0,0", "end_point": "0,100", "colors": ["#f76a6bFF", "#f76a6bFF"], "gradients": [0, 100]}}, "type": "suit", "image_group": null}, "cardbg_with_focus": null}, "user_sailing_v2": {"card_bg": {"id": 5476, "name": "\u5609\u7136\u4eca\u5929\u5403\u4ec0\u4e48", "image": "https://i0.hdslb.com/bfs/garb/item/4442641bd4001214518a81fa8f790ae7469d3cf7.png", "jump_url": "https://www.bilibili.com/h5/mall/equity-link/collect-home?item_id=5476&isdiy=0&part=card_bg&from=reply&f_source=garb&vmid=34859384&native.theme=1&navhide=1", "fan": {"is_fan": 1, "number": 48994, "color": "#f76a6b", "name": "\u5609\u7136\u4eca\u5929\u5403\u4ec0\u4e48", "num_desc": "048994", "num_prefix": "NO.", "color_format": {"start_point": "0,0", "end_point": "0,100", "colors": ["#f76a6bFF", "#f76a6bFF"], "gradients": [0, 100]}}, "type": "suit"}}, "is_contractor": false, "contract_desc": "", "nft_interaction": null, "avatar_item": {"container_size": {"width": 1.8, "height": 1.8}, "fallback_layers": {"layers": [{"visible": true, "general_spec": {"pos_spec": {"coordinate_pos": 2, "axis_x": 0.9, "axis_y": 0.9}, "size_spec": {"width": 1, "height": 1}, "render_spec": {"opacity": 1}}, "layer_config": {"tags": {"AVATAR_LAYER": {}, "GENERAL_CFG": {"config_type": 1, "general_config": {"web_css_style": {"borderRadius": "50%"}}}}, "is_critical": true}, "resource": {"res_type": 3, "res_image": {"image_src": {"src_type": 1, "placeholder": 6, "remote": {"url": "https://i2.hdslb.com/bfs/face/2d4d25f0a89d3f15e49f8ae3d2c53397c042d421.jpg", "bfs_style": "widget-layer-avatar"}}}}}, {"visible": true, "general_spec": {"pos_spec": {"coordinate_pos": 1, "axis_x": 1.025, "axis_y": 1.025}, "size_spec": {"width": 0.41666666666666663, "height": 0.41666666666666663}, "render_spec": {"opacity": 1}}, "layer_config": {"tags": {"GENERAL_CFG": {"config_type": 1, "general_config": {"web_css_style": {"background-color": "rgb(255,255,255)", "border": "2px solid rgba(255,255,255,1)", "borderRadius": "50%", "boxSizing": "border-box"}}}, "ICON_LAYER": {}}}, "resource": {"res_type": 3, "res_image": {"image_src": {"src_type": 2, "local": 1}}}}], "is_critical_group": true}, "mid": "34859384"}}, "content": {"message": "\u6211\u4eec\u7684\u540c\u80de\u53ef\u4ee5\u77e5\u8db3\u53ef\u4ee5\u81ea\u5f97\u5176\u4e50\uff0c\u53ef\u4ee5\u751f\u6d3b\u6e05\u8d2b\u4f46\u7cbe\u795e\u8d4b\u4e88\uff0c\u4e2a\u4eba\u53ef\u4ee5\u5c06\u8fd9\u4e9b\u4f5c\u4e3a\u81ea\u5df1\u4e50\u5929\u7cbe\u795e\u7684\u6b63\u9762\u53cd\u9988\uff0c\u4f46\u662f\u4ece\u793e\u4f1a\u7684\u89d2\u5ea6\u6765\u770b\uff0c\u8fd9\u662f\u4e00\u79cd\u803b\u8fb1", "members": [], "jump_url": {}, "max_line": 6}, "replies": [], "assist": 0, "up_action": {"like": false, "reply": false}, "invisible": false, "reply_control": {"max_line": 6, "time_desc": "14\u5c0f\u65f6\u524d\u53d1\u5e03"}, "folder": {"has_folded": false, "is_folded": false, "rule": ""}, "dynamic_id_str": "0", "note_cvid_str": "0", "track_info": ""}, {"rpid": 230580212880, "oid": 1156233854, "type": 1, "mid": 419223896, "root": 0, "parent": 0, "dialog": 0, "count": 0, "rcount": 0, "state": 0, "fansgrade": 0, "attr": 0, "ctime": 1720544616, "mid_str": "419223896", "oid_str": "1156233854", "rpid_str": "230580212880", "root_str": "0", "parent_str": "0", "dialog_str": "0", "like": 0, "action": 0, "member": {"mid": "419223896", "uname": "Foxeico", "sex": "\u4fdd\u5bc6", "sign": "\u4e8c\u5411\u65e0\u5e38\uff0c\u9047\u800c\u65e0\u5f80", "avatar": "https://i2.hdslb.com/bfs/face/f129fe90c62e373892c4ef4a9abf9434ee54f6e1.webp", "rank": "10000", "face_nft_new": 0, "is_senior_member": 1, "senior": {"status": 2}, "level_info": {"current_level": 6, "current_min": 0, "current_exp": 0, "next_exp": 0}, "pendant": {"pid": 0, "name": "", "image": "", "expire": 0, "image_enhance": "", "image_enhance_frame": "", "n_pid": 0}, "nameplate": {"nid": 3, "name": "\u767d\u94f6\u6bbf\u5802", "image": "https://i1.hdslb.com/bfs/face/f6a31275029365ae5dc710006585ddcf1139bde1.png", "image_small": "https://i1.hdslb.com/bfs/face/b09cdb4c119c467cf2d15db5263b4f539fa6e30b.png", "level": "\u9ad8\u7ea7\u52cb\u7ae0", "condition": "\u5355\u4e2a\u81ea\u5236\u89c6\u9891\u603b\u64ad\u653e\u6570>=10\u4e07"}, "official_verify": {"type": -1, "desc": ""}, "vip": {"vipType": 1, "vipDueDate": 1723305600000, "dueRemark": "", "accessStatus": 0, "vipStatus": 1, "vipStatusWarn": "", "themeType": 0, "label": {"path": "", "text": "\u5927\u4f1a\u5458", "label_theme": "vip", "text_color": "#FFFFFF", "bg_style": 1, "bg_color": "#FB7299", "border_color": "", "use_img_label": true, "img_label_uri_hans": "", "img_label_uri_hant": "", "img_label_uri_hans_static": "https://i0.hdslb.com/bfs/vip/3788b674c69072f1ee252b79a31ecc8c43af3039.png", "img_label_uri_hant_static": "https://i0.hdslb.com/bfs/activity-plat/static/20220614/e369244d0b14644f5e1a06431e22a4d5/jwXBWRVwa5.png"}, "avatar_subscript": 1, "nickname_color": "#FB7299"}, "fans_detail": null, "user_sailing": null, "is_contractor": false, "contract_desc": "", "nft_interaction": {"region": {"type": 1, "icon": "https://i0.hdslb.com/bfs/activity-plat/static/20220506/334553dd7c506a92b88eaf4d59ac8b4d/j8AeXAkEul.gif", "show_status": 1}}, "avatar_item": {"container_size": {"width": 1.8, "height": 1.8}, "fallback_layers": {"layers": [{"visible": true, "general_spec": {"pos_spec": {"coordinate_pos": 2, "axis_x": 0.9, "axis_y": 0.9}, "size_spec": {"width": 1.3, "height": 1.3}, "render_spec": {"opacity": 1}}, "layer_config": {"tags": {"AVATAR_LAYER": {}, "GENERAL_CFG": {"config_type": 1, "general_config": {"web_css_style": {"borderRadius": "50%"}}}}, "is_critical": true}, "resource": {"res_type": 4, "res_animation": {"webp_src": {"src_type": 1, "placeholder": 6, "remote": {"url": "https://i2.hdslb.com/bfs/face/f129fe90c62e373892c4ef4a9abf9434ee54f6e1.webp", "bfs_style": "widget-layer-avatar"}}}}}, {"visible": true, "general_spec": {"pos_spec": {"coordinate_pos": 1, "axis_x": 1.175, "axis_y": 1.175}, "size_spec": {"width": 0.41666666666666663, "height": 0.41666666666666663}, "render_spec": {"opacity": 1}}, "layer_config": {"tags": {"GENERAL_CFG": {"config_type": 1, "general_config": {"web_css_style": {"background-color": "rgb(255,255,255)", "border": "2px solid rgba(255,255,255,1)", "borderRadius": "50%", "boxSizing": "border-box"}}}, "ICON_LAYER": {}}}, "resource": {"res_type": 4, "res_animation": {"webp_src": {"src_type": 1, "placeholder": 5, "remote": {"url": "https://i0.hdslb.com/bfs/activity-plat/static/20220506/334553dd7c506a92b88eaf4d59ac8b4d/j8AeXAkEul.gif", "bfs_style": "widget-layer-avatar"}}}}}], "is_critical_group": true}, "mid": "419223896"}}, "content": {"message": "\u771f\u597d\u554a\uff0c\u6211\u7684\u5c38\u4f53\u6696\u6696\u7684\uff0c\u5f88\u5f00\u5fc3", "members": [], "jump_url": {}, "max_line": 6}, "replies": [], "assist": 0, "up_action": {"like": false, "reply": false}, "invisible": false, "reply_control": {"max_line": 6, "time_desc": "14\u5c0f\u65f6\u524d\u53d1\u5e03"}, "folder": {"has_folded": false, "is_folded": false, "rule": ""}, "dynamic_id_str": "0", "note_cvid_str": "0", "track_info": ""}, {"rpid": 230577403296, "oid": 1156233854, "type": 1, "mid": 33307298, "root": 0, "parent": 0, "dialog": 0, "count": 0, "rcount": 0, "state": 0, "fansgrade": 0, "attr": 0, "ctime": 1720543218, "mid_str": "33307298", "oid_str": "1156233854", "rpid_str": "230577403296", "root_str": "0", "parent_str": "0", "dialog_str": "0", "like": 1, "action": 0, "member": {"mid": "33307298", "uname": "bigbig0776", "sex": "\u7537", "sign": "", "avatar": "https://i2.hdslb.com/bfs/face/b058646243eb18fa33c273de68636aab78d33f3c.jpg", "rank": "10000", "face_nft_new": 0, "is_senior_member": 0, "senior": {}, "level_info": {"current_level": 6, "current_min": 0, "current_exp": 0, "next_exp": 0}, "pendant": {"pid": 0, "name": "", "image": "", "expire": 0, "image_enhance": "", "image_enhance_frame": "", "n_pid": 0}, "nameplate": {"nid": 0, "name": "", "image": "", "image_small": "", "level": "", "condition": ""}, "official_verify": {"type": -1, "desc": ""}, "vip": {"vipType": 0, "vipDueDate": 0, "dueRemark": "", "accessStatus": 0, "vipStatus": 0, "vipStatusWarn": "", "themeType": 0, "label": {"path": "", "text": "", "label_theme": "", "text_color": "", "bg_style": 0, "bg_color": "", "border_color": "", "use_img_label": true, "img_label_uri_hans": "", "img_label_uri_hant": "", "img_label_uri_hans_static": "https://i0.hdslb.com/bfs/vip/d7b702ef65a976b20ed854cbd04cb9e27341bb79.png", "img_label_uri_hant_static": "https://i0.hdslb.com/bfs/activity-plat/static/20220614/e369244d0b14644f5e1a06431e22a4d5/KJunwh19T5.png"}, "avatar_subscript": 0, "nickname_color": ""}, "fans_detail": null, "user_sailing": null, "is_contractor": false, "contract_desc": "", "nft_interaction": null, "avatar_item": {"container_size": {"width": 1.8, "height": 1.8}, "fallback_layers": {"layers": [{"visible": true, "general_spec": {"pos_spec": {"coordinate_pos": 2, "axis_x": 0.9, "axis_y": 0.9}, "size_spec": {"width": 1, "height": 1}, "render_spec": {"opacity": 1}}, "layer_config": {"tags": {"AVATAR_LAYER": {}, "GENERAL_CFG": {"config_type": 1, "general_config": {"web_css_style": {"borderRadius": "50%"}}}}, "is_critical": true}, "resource": {"res_type": 3, "res_image": {"image_src": {"src_type": 1, "placeholder": 6, "remote": {"url": "https://i2.hdslb.com/bfs/face/b058646243eb18fa33c273de68636aab78d33f3c.jpg", "bfs_style": "widget-layer-avatar"}}}}}], "is_critical_group": true}, "mid": "33307298"}}, "content": {"message": "\u5e0c\u671b\u793e\u4f1a\u80fd\u8ba9\u6bcf\u4e2a\u4eba\u6709\u5c0a\u4e25\u7684\u6d3b\u7740\uff01\uff01\uff01", "members": [], "jump_url": {}, "max_line": 6}, "replies": [], "assist": 0, "up_action": {"like": false, "reply": false}, "invisible": false, "reply_control": {"max_line": 6, "time_desc": "14\u5c0f\u65f6\u524d\u53d1\u5e03"}, "folder": {"has_folded": false, "is_folded": false, "rule": ""}, "dynamic_id_str": "0", "note_cvid_str": "0", "track_info": ""}, {"rpid": 230577230976, "oid": 1156233854, "type": 1, "mid": 1922939482, "root": 0, "parent": 0, "dialog": 0, "count": 0, "rcount": 0, "state": 0, "fansgrade": 0, "attr": 0, "ctime": 1720543174, "mid_str": "1922939482", "oid_str": "1156233854", "rpid_str": "230577230976", "root_str": "0", "parent_str": "0", "dialog_str": "0", "like": 0, "action": 0, "member": {"mid": "1922939482", "uname": "\u6709\u8282\u64cd\u7684\u55b5\u55b5", "sex": "\u4fdd\u5bc6", "sign": "", "avatar": "https://i1.hdslb.com/bfs/face/a821c958fd3143bf3da1e7f6c92ea3b0725eb00f.jpg", "rank": "10000", "face_nft_new": 0, "is_senior_member": 0, "senior": {}, "level_info": {"current_level": 2, "current_min": 0, "current_exp": 0, "next_exp": 0}, "pendant": {"pid": 0, "name": "", "image": "", "expire": 0, "image_enhance": "", "image_enhance_frame": "", "n_pid": 0}, "nameplate": {"nid": 0, "name": "", "image": "", "image_small": "", "level": "", "condition": ""}, "official_verify": {"type": -1, "desc": ""}, "vip": {"vipType": 0, "vipDueDate": 0, "dueRemark": "", "accessStatus": 0, "vipStatus": 0, "vipStatusWarn": "", "themeType": 0, "label": {"path": "", "text": "", "label_theme": "", "text_color": "", "bg_style": 0, "bg_color": "", "border_color": "", "use_img_label": true, "img_label_uri_hans": "", "img_label_uri_hant": "", "img_label_uri_hans_static": "https://i0.hdslb.com/bfs/vip/d7b702ef65a976b20ed854cbd04cb9e27341bb79.png", "img_label_uri_hant_static": "https://i0.hdslb.com/bfs/activity-plat/static/20220614/e369244d0b14644f5e1a06431e22a4d5/KJunwh19T5.png"}, "avatar_subscript": 0, "nickname_color": ""}, "fans_detail": null, "user_sailing": null, "is_contractor": false, "contract_desc": "", "nft_interaction": null, "avatar_item": {"container_size": {"width": 1.8, "height": 1.8}, "fallback_layers": {"layers": [{"visible": true, "general_spec": {"pos_spec": {"coordinate_pos": 2, "axis_x": 0.9, "axis_y": 0.9}, "size_spec": {"width": 1, "height": 1}, "render_spec": {"opacity": 1}}, "layer_config": {"tags": {"AVATAR_LAYER": {}, "GENERAL_CFG": {"config_type": 1, "general_config": {"web_css_style": {"borderRadius": "50%"}}}}, "is_critical": true}, "resource": {"res_type": 3, "res_image": {"image_src": {"src_type": 1, "placeholder": 6, "remote": {"url": "https://i1.hdslb.com/bfs/face/a821c958fd3143bf3da1e7f6c92ea3b0725eb00f.jpg", "bfs_style": "widget-layer-avatar"}}}}}], "is_critical_group": true}, "mid": "1922939482"}}, "content": {"message": "\u6211\u7237\u7237\u4e5f\u4e70\u4e86\u8fd9\u4e2a\u6c34\u58f6\u70e7\u6c34\uff0c\u6c34\u5f00\u7684\u7279\u522b\u5feb", "members": [], "jump_url": {}, "max_line": 6}, "replies": [], "assist": 0, "up_action": {"like": false, "reply": false}, "invisible": false, "reply_control": {"max_line": 6, "time_desc": "14\u5c0f\u65f6\u524d\u53d1\u5e03"}, "folder": {"has_folded": false, "is_folded": false, "rule": ""}, "dynamic_id_str": "0", "note_cvid_str": "0", "track_info": ""}, {"rpid": 230575166704, "oid": 1156233854, "type": 1, "mid": 30937840, "root": 0, "parent": 0, "dialog": 0, "count": 0, "rcount": 0, "state": 0, "fansgrade": 0, "attr": 0, "ctime": 1720542266, "mid_str": "30937840", "oid_str": "1156233854", "rpid_str": "230575166704", "root_str": "0", "parent_str": "0", "dialog_str": "0", "like": 0, "action": 0, "member": {"mid": "30937840", "uname": "\u6e90\u5bb6\u5c0f\u8089\u624b", "sex": "\u4fdd\u5bc6", "sign": "", "avatar": "https://i1.hdslb.com/bfs/face/802bf095c3498881572fd6632eb31a9cfb1b7281.jpg", "rank": "10000", "face_nft_new": 0, "is_senior_member": 0, "senior": {}, "level_info": {"current_level": 6, "current_min": 0, "current_exp": 0, "next_exp": 0}, "pendant": {"pid": 0, "name": "", "image": "", "expire": 0, "image_enhance": "", "image_enhance_frame": "", "n_pid": 0}, "nameplate": {"nid": 0, "name": "", "image": "", "image_small": "", "level": "", "condition": ""}, "official_verify": {"type": -1, "desc": ""}, "vip": {"vipType": 2, "vipDueDate": 1728403200000, "dueRemark": "", "accessStatus": 0, "vipStatus": 1, "vipStatusWarn": "", "themeType": 0, "label": {"path": "", "text": "\u5e74\u5ea6\u5927\u4f1a\u5458", "label_theme": "annual_vip", "text_color": "#FFFFFF", "bg_style": 1, "bg_color": "#FB7299", "border_color": "", "use_img_label": true, "img_label_uri_hans": "", "img_label_uri_hant": "", "img_label_uri_hans_static": "https://i0.hdslb.com/bfs/vip/8d4f8bfc713826a5412a0a27eaaac4d6b9ede1d9.png", "img_label_uri_hant_static": "https://i0.hdslb.com/bfs/activity-plat/static/20220614/e369244d0b14644f5e1a06431e22a4d5/VEW8fCC0hg.png"}, "avatar_subscript": 1, "nickname_color": "#FB7299"}, "fans_detail": null, "user_sailing": null, "is_contractor": false, "contract_desc": "", "nft_interaction": null, "avatar_item": {"container_size": {"width": 1.8, "height": 1.8}, "fallback_layers": {"layers": [{"visible": true, "general_spec": {"pos_spec": {"coordinate_pos": 2, "axis_x": 0.9, "axis_y": 0.9}, "size_spec": {"width": 1, "height": 1}, "render_spec": {"opacity": 1}}, "layer_config": {"tags": {"AVATAR_LAYER": {}, "GENERAL_CFG": {"config_type": 1, "general_config": {"web_css_style": {"borderRadius": "50%"}}}}, "is_critical": true}, "resource": {"res_type": 3, "res_image": {"image_src": {"src_type": 1, "placeholder": 6, "remote": {"url": "https://i1.hdslb.com/bfs/face/802bf095c3498881572fd6632eb31a9cfb1b7281.jpg", "bfs_style": "widget-layer-avatar"}}}}}, {"visible": true, "general_spec": {"pos_spec": {"coordinate_pos": 1, "axis_x": 1.025, "axis_y": 1.025}, "size_spec": {"width": 0.41666666666666663, "height": 0.41666666666666663}, "render_spec": {"opacity": 1}}, "layer_config": {"tags": {"GENERAL_CFG": {"config_type": 1, "general_config": {"web_css_style": {"background-color": "rgb(255,255,255)", "border": "2px solid rgba(255,255,255,1)", "borderRadius": "50%", "boxSizing": "border-box"}}}, "ICON_LAYER": {}}}, "resource": {"res_type": 3, "res_image": {"image_src": {"src_type": 2, "local": 1}}}}], "is_critical_group": true}, "mid": "30937840"}}, "content": {"message": "\u5927\u7237\u51b7\u5929\u5c31\u591a\u7a7f\u4e86\u51e0\u4ef6\u5355\u8863", "members": [], "jump_url": {}, "max_line": 6}, "replies": [], "assist": 0, "up_action": {"like": false, "reply": false}, "invisible": false, "reply_control": {"max_line": 6, "time_desc": "15\u5c0f\u65f6\u524d\u53d1\u5e03"}, "folder": {"has_folded": false, "is_folded": false, "rule": ""}, "dynamic_id_str": "0", "note_cvid_str": "0", "track_info": ""}], "upper": {"mid": 660013124, "top": null, "vote": null}, "top": null, "vote": 0, "blacklist": 0, "assist": 0, "mode": 3, "support_mode": [2, 3], "control": {"input_disable": false, "root_input_text": "\u53d1\u4e00\u6761\u53cb\u5584\u7684\u8bc4\u8bba", "child_input_text": "\u53d1\u4e00\u6761\u53cb\u5584\u7684\u8bc4\u8bba", "giveup_input_text": "\u4e0d\u53d1\u6ca1\u5173\u7cfb\uff0c\u8bf7\u7ee7\u7eed\u53cb\u5584\u54e6~", "screenshot_icon_state": 1, "upload_picture_icon_state": 1, "answer_guide_text": "\u9700\u8981\u5347\u7ea7\u6210\u4e3alv2\u4f1a\u5458\u540e\u624d\u53ef\u4ee5\u8bc4\u8bba\uff0c\u5148\u53bb\u7b54\u9898\u8f6c\u6b63\u5427\uff01", "answer_guide_icon_url": "http://i0.hdslb.com/bfs/emote/96940d16602cacbbac796245b7bb99fa9b5c970c.png", "answer_guide_ios_url": "https://www.bilibili.com/h5/newbie/entry?navhide=1&re_src=12", "answer_guide_android_url": "https://www.bilibili.com/h5/newbie/entry?navhide=1&re_src=6", "bg_text": "", "empty_page": null, "show_type": 1, "show_text": "", "web_selection": false, "disable_jump_emote": false, "enable_charged": false, "enable_cm_biz_helper": false, "preload_resources": null}, "folder": {"has_folded": false, "is_folded": false, "rule": ""}}